{"page":513,"lines":[{"words":[{"id":70723,"text":"قُلْ","c_v1":"ﭑ"},{"id":70724,"text":"لِلْمُخَلَّفِينَ","c_v1":"ﭒ"},{"id":70725,"text":"مِنَ","c_v1":"ﭓ"},{"id":70726,"text":"الْأَعْرَابِ","c_v1":"ﭔ"},{"id":70727,"text":"سَتُدْعَوْنَ","c_v1":"ﭕ"},{"id":70728,"text":"إِلَى","c_v1":"ﭖ"},{"id":70729,"text":"قَوْمٍ","c_v1":"ﭗ"},{"id":70730,"text":"أُولِي","c_v1":"ﭘ"},{"id":70731,"text":"بَأْسٍ","c_v1":"ﭙ"},{"id":70732,"text":"شَدِيدٍ","c_v1":"ﭚ"}],"data":{}},{"words":[{"id":70733,"text":"تُقَاتِلُونَهُمْ","c_v1":"ﭛ"},{"id":70734,"text":"أَوْ","c_v1":"ﭜ"},{"id":70735,"text":"يُسْلِمُونَ","c_v1":"ﭝﭞ"},{"id":70736,"text":"فَإِنْ","c_v1":"ﭟ"},{"id":70737,"text":"تُطِيعُوا","c_v1":"ﭠ"},{"id":70738,"text":"يُؤْتِكُمُ","c_v1":"ﭡ"},{"id":70739,"text":"اللَّهُ","c_v1":"ﭢ"},{"id":70740,"text":"أَجْرًا","c_v1":"ﭣ"},{"id":70741,"text":"حَسَنًا","c_v1":"ﭤﭥ"}],"data":{}},{"words":[{"id":70742,"text":"وَإِنْ","c_v1":"ﭦ"},{"id":70743,"text":"تَتَوَلَّوْا","c_v1":"ﭧ"},{"id":70744,"text":"كَمَا","c_v1":"ﭨ"},{"id":70745,"text":"تَوَلَّيْتُمْ","c_v1":"ﭩ"},{"id":70746,"text":"مِنْ","c_v1":"ﭪ"},{"id":70747,"text":"قَبْلُ","c_v1":"ﭫ"},{"id":70748,"text":"يُعَذِّبْكُمْ","c_v1":"ﭬ"},{"id":70749,"text":"عَذَابًا","c_v1":"ﭭ"},{"id":70750,"text":"أَلِيمًا","c_v1":"ﭮ"},{"id":70751,"text":"(16)","type":"end","c_v1":"ﭯ"},{"id":70752,"text":"لَيْسَ","c_v1":"ﭰ"}],"data":{}},{"words":[{"id":70753,"text":"عَلَى","c_v1":"ﭱ"},{"id":70754,"text":"الْأَعْمَى","c_v1":"ﭲ"},{"id":70755,"text":"حَرَجٌ","c_v1":"ﭳ"},{"id":70756,"text":"وَلَا","c_v1":"ﭴ"},{"id":70757,"text":"عَلَى","c_v1":"ﭵ"},{"id":70758,"text":"الْأَعْرَجِ","c_v1":"ﭶ"},{"id":70759,"text":"حَرَجٌ","c_v1":"ﭷ"},{"id":70760,"text":"وَلَا","c_v1":"ﭸ"},{"id":70761,"text":"عَلَى","c_v1":"ﭹ"},{"id":70762,"text":"الْمَرِيضِ","c_v1":"ﭺ"},{"id":70763,"text":"حَرَجٌ","c_v1":"ﭻﭼ"}],"data":{}},{"words":[{"id":70764,"text":"وَمَنْ","c_v1":"ﭽ"},{"id":70765,"text":"يُطِعِ","c_v1":"ﭾ"},{"id":70766,"text":"اللَّهَ","c_v1":"ﭿ"},{"id":70767,"text":"وَرَسُولَهُ","c_v1":"ﮀ"},{"id":70768,"text":"يُدْخِلْهُ","c_v1":"ﮁ"},{"id":70769,"text":"جَنَّاتٍ","c_v1":"ﮂ"},{"id":70770,"text":"تَجْرِي","c_v1":"ﮃ"},{"id":70771,"text":"مِنْ","c_v1":"ﮄ"},{"id":70772,"text":"تَحْتِهَا","c_v1":"ﮅ"},{"id":70773,"text":"الْأَنْهَارُ","c_v1":"ﮆﮇ"}],"data":{}},{"words":[{"id":70774,"text":"وَمَنْ","c_v1":"ﮈ"},{"id":70775,"text":"يَتَوَلَّ","c_v1":"ﮉ"},{"id":70776,"text":"يُعَذِّبْهُ","c_v1":"ﮊ"},{"id":70777,"text":"عَذَابًا","c_v1":"ﮋ"},{"id":70778,"text":"أَلِيمًا","c_v1":"ﮌ"},{"id":70779,"text":"(17)","type":"end","c_v1":"ﮍ"},{"id":70780,"text":"لَقَدْ","c_v1":"ﮎ ﮏ"},{"id":70781,"text":"رَضِيَ","c_v1":"ﮐ"},{"id":70782,"text":"اللَّهُ","c_v1":"ﮑ"},{"id":70783,"text":"عَنِ","c_v1":"ﮒ"}],"data":{}},{"words":[{"id":70784,"text":"الْمُؤْمِنِينَ","c_v1":"ﮓ"},{"id":70785,"text":"إِذْ","c_v1":"ﮔ"},{"id":70786,"text":"يُبَايِعُونَكَ","c_v1":"ﮕ"},{"id":70787,"text":"تَحْتَ","c_v1":"ﮖ"},{"id":70788,"text":"الشَّجَرَةِ","c_v1":"ﮗ"},{"id":70789,"text":"فَعَلِمَ","c_v1":"ﮘ"},{"id":70790,"text":"مَا","c_v1":"ﮙ"},{"id":70791,"text":"فِي","c_v1":"ﮚ"},{"id":70792,"text":"قُلُوبِهِمْ","c_v1":"ﮛ"}],"data":{}},{"words":[{"id":70793,"text":"فَأَنْزَلَ","c_v1":"ﮜ"},{"id":70794,"text":"السَّكِينَةَ","c_v1":"ﮝ"},{"id":70795,"text":"عَلَيْهِمْ","c_v1":"ﮞ"},{"id":70796,"text":"وَأَثَابَهُمْ","c_v1":"ﮟ"},{"id":70797,"text":"فَتْحًا","c_v1":"ﮠ"},{"id":70798,"text":"قَرِيبًا","c_v1":"ﮡ"},{"id":70799,"text":"(18)","type":"end","c_v1":"ﮢ"},{"id":70800,"text":"وَمَغَانِمَ","c_v1":"ﮣ"}],"data":{}},{"words":[{"id":70801,"text":"كَثِيرَةً","c_v1":"ﮤ"},{"id":70802,"text":"يَأْخُذُونَهَا","c_v1":"ﮥﮦ"},{"id":70803,"text":"وَكَانَ","c_v1":"ﮧ"},{"id":70804,"text":"اللَّهُ","c_v1":"ﮨ"},{"id":70805,"text":"عَزِيزًا","c_v1":"ﮩ"},{"id":70806,"text":"حَكِيمًا","c_v1":"ﮪ"},{"id":70807,"text":"(19)","type":"end","c_v1":"ﮫ"},{"id":70808,"text":"وَعَدَكُمُ","c_v1":"ﮬ"},{"id":70809,"text":"اللَّهُ","c_v1":"ﮭ"}],"data":{}},{"words":[{"id":70810,"text":"مَغَانِمَ","c_v1":"ﮮ"},{"id":70811,"text":"كَثِيرَةً","c_v1":"ﮯ"},{"id":70812,"text":"تَأْخُذُونَهَا","c_v1":"ﮰ"},{"id":70813,"text":"فَعَجَّلَ","c_v1":"ﮱ"},{"id":70814,"text":"لَكُمْ","c_v1":"ﯓ"},{"id":70815,"text":"هَذِهِ","c_v1":"ﯔ"},{"id":70816,"text":"وَكَفَّ","c_v1":"ﯕ"},{"id":70817,"text":"أَيْدِيَ","c_v1":"ﯖ"}],"data":{}},{"words":[{"id":70818,"text":"النَّاسِ","c_v1":"ﯗ"},{"id":70819,"text":"عَنْكُمْ","c_v1":"ﯘ"},{"id":70820,"text":"وَلِتَكُونَ","c_v1":"ﯙ"},{"id":70821,"text":"آيَةً","c_v1":"ﯚ"},{"id":70822,"text":"لِلْمُؤْمِنِينَ","c_v1":"ﯛ"},{"id":70823,"text":"وَيَهْدِيَكُمْ","c_v1":"ﯜ"},{"id":70824,"text":"صِرَاطًا","c_v1":"ﯝ"}],"data":{}},{"words":[{"id":70825,"text":"مُسْتَقِيمًا","c_v1":"ﯞ"},{"id":70826,"text":"(20)","type":"end","c_v1":"ﯟ"},{"id":70827,"text":"وَأُخْرَى","c_v1":"ﯠ"},{"id":70828,"text":"لَمْ","c_v1":"ﯡ"},{"id":70829,"text":"تَقْدِرُوا","c_v1":"ﯢ"},{"id":70830,"text":"عَلَيْهَا","c_v1":"ﯣ"},{"id":70831,"text":"قَدْ","c_v1":"ﯤ"},{"id":70832,"text":"أَحَاطَ","c_v1":"ﯥ"},{"id":70833,"text":"اللَّهُ","c_v1":"ﯦ"},{"id":70834,"text":"بِهَا","c_v1":"ﯧﯨ"}],"data":{}},{"words":[{"id":70835,"text":"وَكَانَ","c_v1":"ﯩ"},{"id":70836,"text":"اللَّهُ","c_v1":"ﯪ"},{"id":70837,"text":"عَلَى","c_v1":"ﯫ"},{"id":70838,"text":"كُلِّ","c_v1":"ﯬ"},{"id":70839,"text":"شَيْءٍ","c_v1":"ﯭ"},{"id":70840,"text":"قَدِيرًا","c_v1":"ﯮ"},{"id":70841,"text":"(21)","type":"end","c_v1":"ﯯ"},{"id":70842,"text":"وَلَوْ","c_v1":"ﯰ"},{"id":70843,"text":"قَاتَلَكُمُ","c_v1":"ﯱ"},{"id":70844,"text":"الَّذِينَ","c_v1":"ﯲ"},{"id":70845,"text":"كَفَرُوا","c_v1":"ﯳ"}],"data":{}},{"words":[{"id":70846,"text":"لَوَلَّوُا","c_v1":"ﯴ"},{"id":70847,"text":"الْأَدْبَارَ","c_v1":"ﯵ"},{"id":70848,"text":"ثُمَّ","c_v1":"ﯶ"},{"id":70849,"text":"لَا","c_v1":"ﯷ"},{"id":70850,"text":"يَجِدُونَ","c_v1":"ﯸ"},{"id":70851,"text":"وَلِيًّا","c_v1":"ﯹ"},{"id":70852,"text":"وَلَا","c_v1":"ﯺ"},{"id":70853,"text":"نَصِيرًا","c_v1":"ﯻ"},{"id":70854,"text":"(22)","type":"end","c_v1":"ﯼ"},{"id":70855,"text":"سُنَّةَ","c_v1":"ﯽ"}],"data":{}},{"words":[{"id":70856,"text":"اللَّهِ","c_v1":"ﯾ"},{"id":70857,"text":"الَّتِي","c_v1":"ﯿ"},{"id":70858,"text":"قَدْ","c_v1":"ﰀ"},{"id":70859,"text":"خَلَتْ","c_v1":"ﰁ"},{"id":70860,"text":"مِنْ","c_v1":"ﰂ"},{"id":70861,"text":"قَبْلُ","c_v1":"ﰃﰄ"},{"id":70862,"text":"وَلَنْ","c_v1":"ﰅ"},{"id":70863,"text":"تَجِدَ","c_v1":"ﰆ"},{"id":70864,"text":"لِسُنَّةِ","c_v1":"ﰇ"},{"id":70865,"text":"اللَّهِ","c_v1":"ﰈ"},{"id":70866,"text":"تَبْدِيلًا","c_v1":"ﰉ"},{"id":70867,"text":"(23)","type":"end","c_v1":"ﰊ"}],"data":{}}],"header":"سُورَةُ الفَتۡحِ","juz":26,"ayahs":[{"ayah":"قل للمخلفين من الاعراب ستدعون الى قوم اولي باس شديد تقاتلونهم او يسلمون فان تطيعوا يؤتكم الله اجرا حسنا وان تتولوا كما توليتم من قبل يعذبكم عذابا اليما","suraName":"الفتح","ayahId":16},{"ayah":"ليس على الاعمى حرج ولا على الاعرج حرج ولا على المريض حرج ومن يطع الله ورسوله يدخله جنات تجري من تحتها الانهار ومن يتول يعذبه عذابا اليما","suraName":"الفتح","ayahId":17},{"ayah":"لقد رضي الله عن المؤمنين اذ يبايعونك تحت الشجرة فعلم ما في قلوبهم فانزل السكينة عليهم واثابهم فتحا قريبا","suraName":"الفتح","ayahId":18},{"ayah":"ومغانم كثيرة ياخذونها وكان الله عزيزا حكيما","suraName":"الفتح","ayahId":19},{"ayah":"وعدكم الله مغانم كثيرة تاخذونها فعجل لكم هذه وكف ايدي الناس عنكم ولتكون اية للمؤمنين ويهديكم صراطا مستقيما","suraName":"الفتح","ayahId":20},{"ayah":"واخرى لم تقدروا عليها قد احاط الله بها وكان الله على كل شيء قديرا","suraName":"الفتح","ayahId":21},{"ayah":"ولو قاتلكم الذين كفروا لولوا الادبار ثم لا يجدون وليا ولا نصيرا","suraName":"الفتح","ayahId":22},{"ayah":"سنة الله التي قد خلت من قبل ولن تجد لسنة الله تبديلا","suraName":"الفتح","ayahId":23}]}