{"page":474,"lines":[{"words":[{"id":65200,"text":"إِنَّ","c_v1":"ﭑ"},{"id":65201,"text":"السَّاعَةَ","c_v1":"ﭒ"},{"id":65202,"text":"لَآتِيَةٌ","c_v1":"ﭓ"},{"id":65203,"text":"لَا","c_v1":"ﭔ"},{"id":65204,"text":"رَيْبَ","c_v1":"ﭕ"},{"id":65205,"text":"فِيهَا","c_v1":"ﭖ"},{"id":65206,"text":"وَلَكِنَّ","c_v1":"ﭗ"},{"id":65207,"text":"أَكْثَرَ","c_v1":"ﭘ"},{"id":65208,"text":"النَّاسِ","c_v1":"ﭙ"}],"data":{}},{"words":[{"id":65209,"text":"لَا","c_v1":"ﭚ"},{"id":65210,"text":"يُؤْمِنُونَ","c_v1":"ﭛ"},{"id":65211,"text":"(59)","type":"end","c_v1":"ﭜ"},{"id":65212,"text":"وَقَالَ","c_v1":"ﭝ"},{"id":65213,"text":"رَبُّكُمُ","c_v1":"ﭞ"},{"id":65214,"text":"ادْعُونِي","c_v1":"ﭟ"},{"id":65215,"text":"أَسْتَجِبْ","c_v1":"ﭠ"},{"id":65216,"text":"لَكُمْ","c_v1":"ﭡﭢ"}],"data":{}},{"words":[{"id":65217,"text":"إِنَّ","c_v1":"ﭣ"},{"id":65218,"text":"الَّذِينَ","c_v1":"ﭤ"},{"id":65219,"text":"يَسْتَكْبِرُونَ","c_v1":"ﭥ"},{"id":65220,"text":"عَنْ","c_v1":"ﭦ"},{"id":65221,"text":"عِبَادَتِي","c_v1":"ﭧ"},{"id":65222,"text":"سَيَدْخُلُونَ","c_v1":"ﭨ"},{"id":65223,"text":"جَهَنَّمَ","c_v1":"ﭩ"}],"data":{}},{"words":[{"id":65224,"text":"دَاخِرِينَ","c_v1":"ﭪ"},{"id":65225,"text":"(60)","type":"end","c_v1":"ﭫ"},{"id":65226,"text":"اللَّهُ","c_v1":"ﭬ"},{"id":65227,"text":"الَّذِي","c_v1":"ﭭ"},{"id":65228,"text":"جَعَلَ","c_v1":"ﭮ"},{"id":65229,"text":"لَكُمُ","c_v1":"ﭯ"},{"id":65230,"text":"اللَّيْلَ","c_v1":"ﭰ"},{"id":65231,"text":"لِتَسْكُنُوا","c_v1":"ﭱ"}],"data":{}},{"words":[{"id":65232,"text":"فِيهِ","c_v1":"ﭲ"},{"id":65233,"text":"وَالنَّهَارَ","c_v1":"ﭳ"},{"id":65234,"text":"مُبْصِرًا","c_v1":"ﭴﭵ"},{"id":65235,"text":"إِنَّ","c_v1":"ﭶ"},{"id":65236,"text":"اللَّهَ","c_v1":"ﭷ"},{"id":65237,"text":"لَذُو","c_v1":"ﭸ"},{"id":65238,"text":"فَضْلٍ","c_v1":"ﭹ"},{"id":65239,"text":"عَلَى","c_v1":"ﭺ"},{"id":65240,"text":"النَّاسِ","c_v1":"ﭻ"}],"data":{}},{"words":[{"id":65241,"text":"وَلَكِنَّ","c_v1":"ﭼ"},{"id":65242,"text":"أَكْثَرَ","c_v1":"ﭽ"},{"id":65243,"text":"النَّاسِ","c_v1":"ﭾ"},{"id":65244,"text":"لَا","c_v1":"ﭿ"},{"id":65245,"text":"يَشْكُرُونَ","c_v1":"ﮀ"},{"id":65246,"text":"(61)","type":"end","c_v1":"ﮁ"},{"id":65247,"text":"ذَلِكُمُ","c_v1":"ﮂ"}],"data":{}},{"words":[{"id":65248,"text":"اللَّهُ","c_v1":"ﮃ"},{"id":65249,"text":"رَبُّكُمْ","c_v1":"ﮄ"},{"id":65250,"text":"خَالِقُ","c_v1":"ﮅ"},{"id":65251,"text":"كُلِّ","c_v1":"ﮆ"},{"id":65252,"text":"شَيْءٍ","c_v1":"ﮇ"},{"id":65253,"text":"لَا","c_v1":"ﮈ"},{"id":65254,"text":"إِلَهَ","c_v1":"ﮉ"},{"id":65255,"text":"إِلَّا","c_v1":"ﮊ"},{"id":65256,"text":"هُوَ","c_v1":"ﮋﮌ"},{"id":65257,"text":"فَأَنَّى","c_v1":"ﮍ"},{"id":65258,"text":"تُؤْفَكُونَ","c_v1":"ﮎ"}],"data":{}},{"words":[{"id":65259,"text":"(62)","type":"end","c_v1":"ﮏ"},{"id":65260,"text":"كَذَلِكَ","c_v1":"ﮐ"},{"id":65261,"text":"يُؤْفَكُ","c_v1":"ﮑ"},{"id":65262,"text":"الَّذِينَ","c_v1":"ﮒ"},{"id":65263,"text":"كَانُوا","c_v1":"ﮓ"},{"id":65264,"text":"بِآيَاتِ","c_v1":"ﮔ"},{"id":65265,"text":"اللَّهِ","c_v1":"ﮕ"},{"id":65266,"text":"يَجْحَدُونَ","c_v1":"ﮖ"}],"data":{}},{"words":[{"id":65267,"text":"(63)","type":"end","c_v1":"ﮗ"},{"id":65268,"text":"اللَّهُ","c_v1":"ﮘ"},{"id":65269,"text":"الَّذِي","c_v1":"ﮙ"},{"id":65270,"text":"جَعَلَ","c_v1":"ﮚ"},{"id":65271,"text":"لَكُمُ","c_v1":"ﮛ"},{"id":65272,"text":"الْأَرْضَ","c_v1":"ﮜ"},{"id":65273,"text":"قَرَارًا","c_v1":"ﮝ"},{"id":65274,"text":"وَالسَّمَاءَ","c_v1":"ﮞ"}],"data":{}},{"words":[{"id":65275,"text":"بِنَاءً","c_v1":"ﮟ"},{"id":65276,"text":"وَصَوَّرَكُمْ","c_v1":"ﮠ"},{"id":65277,"text":"فَأَحْسَنَ","c_v1":"ﮡ"},{"id":65278,"text":"صُوَرَكُمْ","c_v1":"ﮢ"},{"id":65279,"text":"وَرَزَقَكُمْ","c_v1":"ﮣ"},{"id":65280,"text":"مِنَ","c_v1":"ﮤ"}],"data":{}},{"words":[{"id":65281,"text":"الطَّيِّبَاتِ","c_v1":"ﮥﮦ"},{"id":65282,"text":"ذَلِكُمُ","c_v1":"ﮧ"},{"id":65283,"text":"اللَّهُ","c_v1":"ﮨ"},{"id":65284,"text":"رَبُّكُمْ","c_v1":"ﮩﮪ"},{"id":65285,"text":"فَتَبَارَكَ","c_v1":"ﮫ"},{"id":65286,"text":"اللَّهُ","c_v1":"ﮬ"},{"id":65287,"text":"رَبُّ","c_v1":"ﮭ"}],"data":{}},{"words":[{"id":65288,"text":"الْعَالَمِينَ","c_v1":"ﮮ"},{"id":65289,"text":"(64)","type":"end","c_v1":"ﮯ"},{"id":65290,"text":"هُوَ","c_v1":"ﮰ"},{"id":65291,"text":"الْحَيُّ","c_v1":"ﮱ"},{"id":65292,"text":"لَا","c_v1":"ﯓ"},{"id":65293,"text":"إِلَهَ","c_v1":"ﯔ"},{"id":65294,"text":"إِلَّا","c_v1":"ﯕ"},{"id":65295,"text":"هُوَ","c_v1":"ﯖ"},{"id":65296,"text":"فَادْعُوهُ","c_v1":"ﯗ"}],"data":{}},{"words":[{"id":65297,"text":"مُخْلِصِينَ","c_v1":"ﯘ"},{"id":65298,"text":"لَهُ","c_v1":"ﯙ"},{"id":65299,"text":"الدِّينَ","c_v1":"ﯚﯛ"},{"id":65300,"text":"الْحَمْدُ","c_v1":"ﯜ"},{"id":65301,"text":"لِلَّهِ","c_v1":"ﯝ"},{"id":65302,"text":"رَبِّ","c_v1":"ﯞ"},{"id":65303,"text":"الْعَالَمِينَ","c_v1":"ﯟ"},{"id":65304,"text":"(65)","type":"end","c_v1":"ﯠ"},{"id":65305,"text":"قُلْ","c_v1":"ﯡ ﯢ"}],"data":{}},{"words":[{"id":65306,"text":"إِنِّي","c_v1":"ﯣ"},{"id":65307,"text":"نُهِيتُ","c_v1":"ﯤ"},{"id":65308,"text":"أَنْ","c_v1":"ﯥ"},{"id":65309,"text":"أَعْبُدَ","c_v1":"ﯦ"},{"id":65310,"text":"الَّذِينَ","c_v1":"ﯧ"},{"id":65311,"text":"تَدْعُونَ","c_v1":"ﯨ"},{"id":65312,"text":"مِنْ","c_v1":"ﯩ"},{"id":65313,"text":"دُونِ","c_v1":"ﯪ"},{"id":65314,"text":"اللَّهِ","c_v1":"ﯫ"},{"id":65315,"text":"لَمَّا","c_v1":"ﯬ"},{"id":65316,"text":"جَاءَنِيَ","c_v1":"ﯭ"}],"data":{}},{"words":[{"id":65317,"text":"الْبَيِّنَاتُ","c_v1":"ﯮ"},{"id":65318,"text":"مِنْ","c_v1":"ﯯ"},{"id":65319,"text":"رَبِّي","c_v1":"ﯰ"},{"id":65320,"text":"وَأُمِرْتُ","c_v1":"ﯱ"},{"id":65321,"text":"أَنْ","c_v1":"ﯲ"},{"id":65322,"text":"أُسْلِمَ","c_v1":"ﯳ"},{"id":65323,"text":"لِرَبِّ","c_v1":"ﯴ"},{"id":65324,"text":"الْعَالَمِينَ","c_v1":"ﯵ"},{"id":65325,"text":"(66)","type":"end","c_v1":"ﯶ"}],"data":{}}],"header":"سُورَةُ غَافِرٍ","juz":24,"ayahs":[{"ayah":"ان الساعة لاتية لا ريب فيها ولكن اكثر الناس لا يؤمنون","suraName":"غافر","ayahId":59},{"ayah":"وقال ربكم ادعوني استجب لكم ان الذين يستكبرون عن عبادتي سيدخلون جهنم داخرين","suraName":"غافر","ayahId":60},{"ayah":"الله الذي جعل لكم الليل لتسكنوا فيه والنهار مبصرا ان الله لذو فضل على الناس ولكن اكثر الناس لا يشكرون","suraName":"غافر","ayahId":61},{"ayah":"ذلكم الله ربكم خالق كل شيء لا اله الا هو فانى تؤفكون","suraName":"غافر","ayahId":62},{"ayah":"كذلك يؤفك الذين كانوا بايات الله يجحدون","suraName":"غافر","ayahId":63},{"ayah":"الله الذي جعل لكم الارض قرارا والسماء بناء وصوركم فاحسن صوركم ورزقكم من الطيبات ذلكم الله ربكم فتبارك الله رب العالمين","suraName":"غافر","ayahId":64},{"ayah":"هو الحي لا اله الا هو فادعوه مخلصين له الدين الحمد لله رب العالمين","suraName":"غافر","ayahId":65},{"ayah":"قل اني نهيت ان اعبد الذين تدعون من دون الله لما جاءني البينات من ربي وامرت ان اسلم لرب العالمين","suraName":"غافر","ayahId":66}]}