{"page":298,"lines":[{"words":[{"id":40284,"text":"وَدَخَلَ","c_v1":"ﭑ"},{"id":40285,"text":"جَنَّتَهُ","c_v1":"ﭒ"},{"id":40286,"text":"وَهُوَ","c_v1":"ﭓ"},{"id":40287,"text":"ظَالِمٌ","c_v1":"ﭔ"},{"id":40288,"text":"لِنَفْسِهِ","c_v1":"ﭕ"},{"id":40289,"text":"قَالَ","c_v1":"ﭖ"},{"id":40290,"text":"مَا","c_v1":"ﭗ"},{"id":40291,"text":"أَظُنُّ","c_v1":"ﭘ"},{"id":40292,"text":"أَنْ","c_v1":"ﭙ"},{"id":40293,"text":"تَبِيدَ","c_v1":"ﭚ"},{"id":40294,"text":"هَذِهِ","c_v1":"ﭛ"}],"data":{}},{"words":[{"id":40295,"text":"أَبَدًا","type":"end","c_v1":"ﭜ"},{"id":40296,"text":"(35)","c_v1":"ﭝ"},{"id":40297,"text":"وَمَا","c_v1":"ﭞ"},{"id":40298,"text":"أَظُنُّ","c_v1":"ﭟ"},{"id":40299,"text":"السَّاعَةَ","c_v1":"ﭠ"},{"id":40300,"text":"قَائِمَةً","c_v1":"ﭡ"},{"id":40301,"text":"وَلَئِنْ","c_v1":"ﭢ"},{"id":40302,"text":"رُدِدْتُ","c_v1":"ﭣ"},{"id":40303,"text":"إِلَى","c_v1":"ﭤ"},{"id":40304,"text":"رَبِّي","c_v1":"ﭥ"}],"data":{}},{"words":[{"id":40305,"text":"لَأَجِدَنَّ","c_v1":"ﭦ"},{"id":40306,"text":"خَيْرًا","c_v1":"ﭧ"},{"id":40307,"text":"مِنْهَا","c_v1":"ﭨ"},{"id":40308,"text":"مُنْقَلَبًا","type":"end","c_v1":"ﭩ"},{"id":40309,"text":"(36)","c_v1":"ﭪ"},{"id":40310,"text":"قَالَ","c_v1":"ﭫ"},{"id":40311,"text":"لَهُ","c_v1":"ﭬ"},{"id":40312,"text":"صَاحِبُهُ","c_v1":"ﭭ"},{"id":40313,"text":"وَهُوَ","c_v1":"ﭮ"},{"id":40314,"text":"يُحَاوِرُهُ","c_v1":"ﭯ"}],"data":{}},{"words":[{"id":40315,"text":"أَكَفَرْتَ","c_v1":"ﭰ"},{"id":40316,"text":"بِالَّذِي","c_v1":"ﭱ"},{"id":40317,"text":"خَلَقَكَ","c_v1":"ﭲ"},{"id":40318,"text":"مِنْ","c_v1":"ﭳ"},{"id":40319,"text":"تُرَابٍ","c_v1":"ﭴ"},{"id":40320,"text":"ثُمَّ","c_v1":"ﭵ"},{"id":40321,"text":"مِنْ","c_v1":"ﭶ"},{"id":40322,"text":"نُطْفَةٍ","c_v1":"ﭷ"},{"id":40323,"text":"ثُمَّ","c_v1":"ﭸ"},{"id":40324,"text":"سَوَّاكَ","c_v1":"ﭹ"},{"id":40325,"text":"رَجُلًا","type":"end","c_v1":"ﭺ"}],"data":{}},{"words":[{"id":40326,"text":"(37)","c_v1":"ﭻ"},{"id":40327,"text":"لَكِنَّا","c_v1":"ﭼ"},{"id":40328,"text":"هُوَ","c_v1":"ﭽ"},{"id":40329,"text":"اللَّهُ","c_v1":"ﭾ"},{"id":40330,"text":"رَبِّي","c_v1":"ﭿ"},{"id":40331,"text":"وَلَا","c_v1":"ﮀ"},{"id":40332,"text":"أُشْرِكُ","c_v1":"ﮁ"},{"id":40333,"text":"بِرَبِّي","c_v1":"ﮂ"},{"id":40334,"text":"أَحَدًا","type":"end","c_v1":"ﮃ"},{"id":40335,"text":"(38)","c_v1":"ﮄ"},{"id":40336,"text":"وَلَوْلَا","c_v1":"ﮅ"},{"id":40337,"text":"إِذْ","c_v1":"ﮆ"}],"data":{}},{"words":[{"id":40338,"text":"دَخَلْتَ","c_v1":"ﮇ"},{"id":40339,"text":"جَنَّتَكَ","c_v1":"ﮈ"},{"id":40340,"text":"قُلْتَ","c_v1":"ﮉ"},{"id":40341,"text":"مَا","c_v1":"ﮊ"},{"id":40342,"text":"شَاءَ","c_v1":"ﮋ"},{"id":40343,"text":"اللَّهُ","c_v1":"ﮌ"},{"id":40344,"text":"لَا","c_v1":"ﮍ"},{"id":40345,"text":"قُوَّةَ","c_v1":"ﮎ"},{"id":40346,"text":"إِلَّا","c_v1":"ﮏ"},{"id":40347,"text":"بِاللَّهِ","c_v1":"ﮐﮑ"},{"id":40348,"text":"إِنْ","c_v1":"ﮒ"},{"id":40349,"text":"تَرَنِ","c_v1":"ﮓ"},{"id":40350,"text":"أَنَا","c_v1":"ﮔ"}],"data":{}},{"words":[{"id":40351,"text":"أَقَلَّ","c_v1":"ﮕ"},{"id":40352,"text":"مِنْكَ","c_v1":"ﮖ"},{"id":40353,"text":"مَالًا","c_v1":"ﮗ"},{"id":40354,"text":"وَوَلَدًا","type":"end","c_v1":"ﮘ"},{"id":40355,"text":"(39)","c_v1":"ﮙ"},{"id":40356,"text":"فَعَسَى","c_v1":"ﮚ"},{"id":40357,"text":"رَبِّي","c_v1":"ﮛ"},{"id":40358,"text":"أَنْ","c_v1":"ﮜ"},{"id":40359,"text":"يُؤْتِيَنِ","c_v1":"ﮝ"},{"id":40360,"text":"خَيْرًا","c_v1":"ﮞ"},{"id":40361,"text":"مِنْ","c_v1":"ﮟ"}],"data":{}},{"words":[{"id":40362,"text":"جَنَّتِكَ","c_v1":"ﮠ"},{"id":40363,"text":"وَيُرْسِلَ","c_v1":"ﮡ"},{"id":40364,"text":"عَلَيْهَا","c_v1":"ﮢ"},{"id":40365,"text":"حُسْبَانًا","c_v1":"ﮣ"},{"id":40366,"text":"مِنَ","c_v1":"ﮤ"},{"id":40367,"text":"السَّمَاءِ","c_v1":"ﮥ"},{"id":40368,"text":"فَتُصْبِحَ","c_v1":"ﮦ"},{"id":40369,"text":"صَعِيدًا","c_v1":"ﮧ"}],"data":{}},{"words":[{"id":40370,"text":"زَلَقًا","type":"end","c_v1":"ﮨ"},{"id":40371,"text":"(40)","c_v1":"ﮩ"},{"id":40372,"text":"أَوْ","c_v1":"ﮪ"},{"id":40373,"text":"يُصْبِحَ","c_v1":"ﮫ"},{"id":40374,"text":"مَاؤُهَا","c_v1":"ﮬ"},{"id":40375,"text":"غَوْرًا","c_v1":"ﮭ"},{"id":40376,"text":"فَلَنْ","c_v1":"ﮮ"},{"id":40377,"text":"تَسْتَطِيعَ","c_v1":"ﮯ"},{"id":40378,"text":"لَهُ","c_v1":"ﮰ"},{"id":40379,"text":"طَلَبًا","type":"end","c_v1":"ﮱ"},{"id":40380,"text":"(41)","c_v1":"ﯓ"}],"data":{}},{"words":[{"id":40381,"text":"وَأُحِيطَ","c_v1":"ﯔ"},{"id":40382,"text":"بِثَمَرِهِ","c_v1":"ﯕ"},{"id":40383,"text":"فَأَصْبَحَ","c_v1":"ﯖ"},{"id":40384,"text":"يُقَلِّبُ","c_v1":"ﯗ"},{"id":40385,"text":"كَفَّيْهِ","c_v1":"ﯘ"},{"id":40386,"text":"عَلَى","c_v1":"ﯙ"},{"id":40387,"text":"مَا","c_v1":"ﯚ"},{"id":40388,"text":"أَنْفَقَ","c_v1":"ﯛ"},{"id":40389,"text":"فِيهَا","c_v1":"ﯜ"},{"id":40390,"text":"وَهِيَ","c_v1":"ﯝ"},{"id":40391,"text":"خَاوِيَةٌ","c_v1":"ﯞ"}],"data":{}},{"words":[{"id":40392,"text":"عَلَى","c_v1":"ﯟ"},{"id":40393,"text":"عُرُوشِهَا","c_v1":"ﯠ"},{"id":40394,"text":"وَيَقُولُ","c_v1":"ﯡ"},{"id":40395,"text":"يالَيْتَنِي","c_v1":"ﯢ"},{"id":40396,"text":"لَمْ","c_v1":"ﯣ"},{"id":40397,"text":"أُشْرِكْ","c_v1":"ﯤ"},{"id":40398,"text":"بِرَبِّي","c_v1":"ﯥ"},{"id":40399,"text":"أَحَدًا","type":"end","c_v1":"ﯦ"},{"id":40400,"text":"(42)","c_v1":"ﯧ"},{"id":40401,"text":"وَلَمْ","c_v1":"ﯨ"},{"id":40402,"text":"تَكُنْ","c_v1":"ﯩ"},{"id":40403,"text":"لَهُ","c_v1":"ﯪ"}],"data":{}},{"words":[{"id":40404,"text":"فِئَةٌ","c_v1":"ﯫ"},{"id":40405,"text":"يَنْصُرُونَهُ","c_v1":"ﯬ"},{"id":40406,"text":"مِنْ","c_v1":"ﯭ"},{"id":40407,"text":"دُونِ","c_v1":"ﯮ"},{"id":40408,"text":"اللَّهِ","c_v1":"ﯯ"},{"id":40409,"text":"وَمَا","c_v1":"ﯰ"},{"id":40410,"text":"كَانَ","c_v1":"ﯱ"},{"id":40411,"text":"مُنْتَصِرًا","type":"end","c_v1":"ﯲ"},{"id":40412,"text":"(43)","c_v1":"ﯳ"},{"id":40413,"text":"هُنَالِكَ","c_v1":"ﯴ"},{"id":40414,"text":"الْوَلَايَةُ","c_v1":"ﯵ"}],"data":{}},{"words":[{"id":40415,"text":"لِلَّهِ","c_v1":"ﯶ"},{"id":40416,"text":"الْحَقِّ","c_v1":"ﯷﯸ"},{"id":40417,"text":"هُوَ","c_v1":"ﯹ"},{"id":40418,"text":"خَيْرٌ","c_v1":"ﯺ"},{"id":40419,"text":"ثَوَابًا","c_v1":"ﯻ"},{"id":40420,"text":"وَخَيْرٌ","c_v1":"ﯼ"},{"id":40421,"text":"عُقْبًا","type":"end","c_v1":"ﯽ"},{"id":40422,"text":"(44)","c_v1":"ﯾ"},{"id":40423,"text":"وَاضْرِبْ","c_v1":"ﯿ"},{"id":40424,"text":"لَهُمْ","c_v1":"ﰀ"},{"id":40425,"text":"مَثَلَ","c_v1":"ﰁ"},{"id":40426,"text":"الْحَيَاةِ","c_v1":"ﰂ"}],"data":{}},{"words":[{"id":40427,"text":"الدُّنْيَا","c_v1":"ﰃ"},{"id":40428,"text":"كَمَاءٍ","c_v1":"ﰄ"},{"id":40429,"text":"أَنْزَلْنَاهُ","c_v1":"ﰅ"},{"id":40430,"text":"مِنَ","c_v1":"ﰆ"},{"id":40431,"text":"السَّمَاءِ","c_v1":"ﰇ"},{"id":40432,"text":"فَاخْتَلَطَ","c_v1":"ﰈ"},{"id":40433,"text":"بِهِ","c_v1":"ﰉ"},{"id":40434,"text":"نَبَاتُ","c_v1":"ﰊ"},{"id":40435,"text":"الْأَرْضِ","c_v1":"ﰋ"}],"data":{}},{"words":[{"id":40436,"text":"فَأَصْبَحَ","c_v1":"ﰌ"},{"id":40437,"text":"هَشِيمًا","c_v1":"ﰍ"},{"id":40438,"text":"تَذْرُوهُ","c_v1":"ﰎ"},{"id":40439,"text":"الرِّيَاحُ","c_v1":"ﰏﰐ"},{"id":40440,"text":"وَكَانَ","c_v1":"ﰑ"},{"id":40441,"text":"اللَّهُ","c_v1":"ﰒ"},{"id":40442,"text":"عَلَى","c_v1":"ﰓ"},{"id":40443,"text":"كُلِّ","c_v1":"ﰔ"},{"id":40444,"text":"شَيْءٍ","c_v1":"ﰕ"},{"id":40445,"text":"مُقْتَدِرًا","type":"end","c_v1":"ﰖ"},{"id":40446,"text":"(45)","c_v1":"ﰗ"}],"data":{}}],"header":"سُورَةُ الكَهۡفِ","juz":15,"ayahs":[{"ayah":"ودخل جنته وهو ظالم لنفسه قال ما اظن ان تبيد هذه ابدا","suraName":"الكهف","ayahId":35},{"ayah":"وما اظن الساعة قائمة ولئن رددت الى ربي لاجدن خيرا منها منقلبا","suraName":"الكهف","ayahId":36},{"ayah":"قال له صاحبه وهو يحاوره اكفرت بالذي خلقك من تراب ثم من نطفة ثم سواك رجلا","suraName":"الكهف","ayahId":37},{"ayah":"لكنا هو الله ربي ولا اشرك بربي احدا","suraName":"الكهف","ayahId":38},{"ayah":"ولولا اذ دخلت جنتك قلت ما شاء الله لا قوة الا بالله ان ترن انا اقل منك مالا وولدا","suraName":"الكهف","ayahId":39},{"ayah":"فعسى ربي ان يؤتين خيرا من جنتك ويرسل عليها حسبانا من السماء فتصبح صعيدا زلقا","suraName":"الكهف","ayahId":40},{"ayah":"او يصبح ماؤها غورا فلن تستطيع له طلبا","suraName":"الكهف","ayahId":41},{"ayah":"واحيط بثمره فاصبح يقلب كفيه على ما انفق فيها وهي خاوية على عروشها ويقول ياليتني لم اشرك بربي احدا","suraName":"الكهف","ayahId":42},{"ayah":"ولم تكن له فئة ينصرونه من دون الله وما كان منتصرا","suraName":"الكهف","ayahId":43},{"ayah":"هنالك الولاية لله الحق هو خير ثوابا وخير عقبا","suraName":"الكهف","ayahId":44},{"ayah":"واضرب لهم مثل الحياة الدنيا كماء انزلناه من السماء فاختلط به نبات الارض فاصبح هشيما تذروه الرياح وكان الله على كل شيء مقتدرا","suraName":"الكهف","ayahId":45}]}