{"page":368,"lines":[{"words":[{"id":50205,"text":"قَالَ","c_v1":"ﭑ"},{"id":50206,"text":"فَعَلْتُهَا","c_v1":"ﭒ"},{"id":50207,"text":"إِذًا","c_v1":"ﭓ"},{"id":50208,"text":"وَأَنَا","c_v1":"ﭔ"},{"id":50209,"text":"مِنَ","c_v1":"ﭕ"},{"id":50210,"text":"الضَّالِّينَ","type":"end","c_v1":"ﭖ"},{"id":50211,"text":"(20)","c_v1":"ﭗ"},{"id":50212,"text":"فَفَرَرْتُ","c_v1":"ﭘ"},{"id":50213,"text":"مِنْكُمْ","c_v1":"ﭙ"},{"id":50214,"text":"لَمَّا","c_v1":"ﭚ"},{"id":50215,"text":"خِفْتُكُمْ","c_v1":"ﭛ"}],"data":{}},{"words":[{"id":50216,"text":"فَوَهَبَ","c_v1":"ﭜ"},{"id":50217,"text":"لِي","c_v1":"ﭝ"},{"id":50218,"text":"رَبِّي","c_v1":"ﭞ"},{"id":50219,"text":"حُكْمًا","c_v1":"ﭟ"},{"id":50220,"text":"وَجَعَلَنِي","c_v1":"ﭠ"},{"id":50221,"text":"مِنَ","c_v1":"ﭡ"},{"id":50222,"text":"الْمُرْسَلِينَ","type":"end","c_v1":"ﭢ"},{"id":50223,"text":"(21)","c_v1":"ﭣ"},{"id":50224,"text":"وَتِلْكَ","c_v1":"ﭤ"},{"id":50225,"text":"نِعْمَةٌ","c_v1":"ﭥ"},{"id":50226,"text":"تَمُنُّهَا","c_v1":"ﭦ"}],"data":{}},{"words":[{"id":50227,"text":"عَلَيَّ","c_v1":"ﭧ"},{"id":50228,"text":"أَنْ","c_v1":"ﭨ"},{"id":50229,"text":"عَبَّدْتَ","c_v1":"ﭩ"},{"id":50230,"text":"بَنِي","c_v1":"ﭪ"},{"id":50231,"text":"إِسْرَائِيلَ","type":"end","c_v1":"ﭫ"},{"id":50232,"text":"(22)","c_v1":"ﭬ"},{"id":50233,"text":"قَالَ","c_v1":"ﭭ"},{"id":50234,"text":"فِرْعَوْنُ","c_v1":"ﭮ"},{"id":50235,"text":"وَمَا","c_v1":"ﭯ"},{"id":50236,"text":"رَبُّ","c_v1":"ﭰ"},{"id":50237,"text":"الْعَالَمِينَ","type":"end","c_v1":"ﭱ"}],"data":{}},{"words":[{"id":50238,"text":"(23)","c_v1":"ﭲ"},{"id":50239,"text":"قَالَ","c_v1":"ﭳ"},{"id":50240,"text":"رَبُّ","c_v1":"ﭴ"},{"id":50241,"text":"السَّمَاوَاتِ","c_v1":"ﭵ"},{"id":50242,"text":"وَالْأَرْضِ","c_v1":"ﭶ"},{"id":50243,"text":"وَمَا","c_v1":"ﭷ"},{"id":50244,"text":"بَيْنَهُمَا","c_v1":"ﭸﭹ"},{"id":50245,"text":"إِنْ","c_v1":"ﭺ"},{"id":50246,"text":"كُنْتُمْ","c_v1":"ﭻ"},{"id":50247,"text":"مُوقِنِينَ","type":"end","c_v1":"ﭼ"}],"data":{}},{"words":[{"id":50248,"text":"(24)","c_v1":"ﭽ"},{"id":50249,"text":"قَالَ","c_v1":"ﭾ"},{"id":50250,"text":"لِمَنْ","c_v1":"ﭿ"},{"id":50251,"text":"حَوْلَهُ","c_v1":"ﮀ"},{"id":50252,"text":"أَلَا","c_v1":"ﮁ"},{"id":50253,"text":"تَسْتَمِعُونَ","type":"end","c_v1":"ﮂ"},{"id":50254,"text":"(25)","c_v1":"ﮃ"},{"id":50255,"text":"قَالَ","c_v1":"ﮄ"},{"id":50256,"text":"رَبُّكُمْ","c_v1":"ﮅ"},{"id":50257,"text":"وَرَبُّ","c_v1":"ﮆ"},{"id":50258,"text":"آبَائِكُمُ","c_v1":"ﮇ"}],"data":{}},{"words":[{"id":50259,"text":"الْأَوَّلِينَ","type":"end","c_v1":"ﮈ"},{"id":50260,"text":"(26)","c_v1":"ﮉ"},{"id":50261,"text":"قَالَ","c_v1":"ﮊ"},{"id":50262,"text":"إِنَّ","c_v1":"ﮋ"},{"id":50263,"text":"رَسُولَكُمُ","c_v1":"ﮌ"},{"id":50264,"text":"الَّذِي","c_v1":"ﮍ"},{"id":50265,"text":"أُرْسِلَ","c_v1":"ﮎ"},{"id":50266,"text":"إِلَيْكُمْ","c_v1":"ﮏ"},{"id":50267,"text":"لَمَجْنُونٌ","type":"end","c_v1":"ﮐ"},{"id":50268,"text":"(27)","c_v1":"ﮑ"}],"data":{}},{"words":[{"id":50269,"text":"قَالَ","c_v1":"ﮒ"},{"id":50270,"text":"رَبُّ","c_v1":"ﮓ"},{"id":50271,"text":"الْمَشْرِقِ","c_v1":"ﮔ"},{"id":50272,"text":"وَالْمَغْرِبِ","c_v1":"ﮕ"},{"id":50273,"text":"وَمَا","c_v1":"ﮖ"},{"id":50274,"text":"بَيْنَهُمَا","c_v1":"ﮗﮘ"},{"id":50275,"text":"إِنْ","c_v1":"ﮙ"},{"id":50276,"text":"كُنْتُمْ","c_v1":"ﮚ"},{"id":50277,"text":"تَعْقِلُونَ","type":"end","c_v1":"ﮛ"},{"id":50278,"text":"(28)","c_v1":"ﮜ"},{"id":50279,"text":"قَالَ","c_v1":"ﮝ"}],"data":{}},{"words":[{"id":50280,"text":"لَئِنِ","c_v1":"ﮞ"},{"id":50281,"text":"اتَّخَذْتَ","c_v1":"ﮟ"},{"id":50282,"text":"إِلَهًا","c_v1":"ﮠ"},{"id":50283,"text":"غَيْرِي","c_v1":"ﮡ"},{"id":50284,"text":"لَأَجْعَلَنَّكَ","c_v1":"ﮢ"},{"id":50285,"text":"مِنَ","c_v1":"ﮣ"},{"id":50286,"text":"الْمَسْجُونِينَ","type":"end","c_v1":"ﮤ"},{"id":50287,"text":"(29)","c_v1":"ﮥ"},{"id":50288,"text":"قَالَ","c_v1":"ﮦ"}],"data":{}},{"words":[{"id":50289,"text":"أَوَلَوْ","c_v1":"ﮧ"},{"id":50290,"text":"جِئْتُكَ","c_v1":"ﮨ"},{"id":50291,"text":"بِشَيْءٍ","c_v1":"ﮩ"},{"id":50292,"text":"مُبِينٍ","type":"end","c_v1":"ﮪ"},{"id":50293,"text":"(30)","c_v1":"ﮫ"},{"id":50294,"text":"قَالَ","c_v1":"ﮬ"},{"id":50295,"text":"فَأْتِ","c_v1":"ﮭ"},{"id":50296,"text":"بِهِ","c_v1":"ﮮ"},{"id":50297,"text":"إِنْ","c_v1":"ﮯ"},{"id":50298,"text":"كُنْتَ","c_v1":"ﮰ"},{"id":50299,"text":"مِنَ","c_v1":"ﮱ"}],"data":{}},{"words":[{"id":50300,"text":"الصَّادِقِينَ","type":"end","c_v1":"ﯓ"},{"id":50301,"text":"(31)","c_v1":"ﯔ"},{"id":50302,"text":"فَأَلْقَى","c_v1":"ﯕ"},{"id":50303,"text":"عَصَاهُ","c_v1":"ﯖ"},{"id":50304,"text":"فَإِذَا","c_v1":"ﯗ"},{"id":50305,"text":"هِيَ","c_v1":"ﯘ"},{"id":50306,"text":"ثُعْبَانٌ","c_v1":"ﯙ"},{"id":50307,"text":"مُبِينٌ","type":"end","c_v1":"ﯚ"},{"id":50308,"text":"(32)","c_v1":"ﯛ"},{"id":50309,"text":"وَنَزَعَ","c_v1":"ﯜ"},{"id":50310,"text":"يَدَهُ","c_v1":"ﯝ"}],"data":{}},{"words":[{"id":50311,"text":"فَإِذَا","c_v1":"ﯞ"},{"id":50312,"text":"هِيَ","c_v1":"ﯟ"},{"id":50313,"text":"بَيْضَاءُ","c_v1":"ﯠ"},{"id":50314,"text":"لِلنَّاظِرِينَ","type":"end","c_v1":"ﯡ"},{"id":50315,"text":"(33)","c_v1":"ﯢ"},{"id":50316,"text":"قَالَ","c_v1":"ﯣ"},{"id":50317,"text":"لِلْمَلَإِ","c_v1":"ﯤ"},{"id":50318,"text":"حَوْلَهُ","c_v1":"ﯥ"},{"id":50319,"text":"إِنَّ","c_v1":"ﯦ"},{"id":50320,"text":"هَذَا","c_v1":"ﯧ"},{"id":50321,"text":"لَسَاحِرٌ","c_v1":"ﯨ"}],"data":{}},{"words":[{"id":50322,"text":"عَلِيمٌ","type":"end","c_v1":"ﯩ"},{"id":50323,"text":"(34)","c_v1":"ﯪ"},{"id":50324,"text":"يُرِيدُ","c_v1":"ﯫ"},{"id":50325,"text":"أَنْ","c_v1":"ﯬ"},{"id":50326,"text":"يُخْرِجَكُمْ","c_v1":"ﯭ"},{"id":50327,"text":"مِنْ","c_v1":"ﯮ"},{"id":50328,"text":"أَرْضِكُمْ","c_v1":"ﯯ"},{"id":50329,"text":"بِسِحْرِهِ","c_v1":"ﯰ"},{"id":50330,"text":"فَمَاذَا","c_v1":"ﯱ"}],"data":{}},{"words":[{"id":50331,"text":"تَأْمُرُونَ","type":"end","c_v1":"ﯲ"},{"id":50332,"text":"(35)","c_v1":"ﯳ"},{"id":50333,"text":"قَالُوا","c_v1":"ﯴ"},{"id":50334,"text":"أَرْجِهْ","c_v1":"ﯵ"},{"id":50335,"text":"وَأَخَاهُ","c_v1":"ﯶ"},{"id":50336,"text":"وَابْعَثْ","c_v1":"ﯷ"},{"id":50337,"text":"فِي","c_v1":"ﯸ"},{"id":50338,"text":"الْمَدَائِنِ","c_v1":"ﯹ"},{"id":50339,"text":"حَاشِرِينَ","type":"end","c_v1":"ﯺ"}],"data":{}},{"words":[{"id":50340,"text":"(36)","c_v1":"ﯻ"},{"id":50341,"text":"يَأْتُوكَ","c_v1":"ﯼ"},{"id":50342,"text":"بِكُلِّ","c_v1":"ﯽ"},{"id":50343,"text":"سَحَّارٍ","c_v1":"ﯾ"},{"id":50344,"text":"عَلِيمٍ","type":"end","c_v1":"ﯿ"},{"id":50345,"text":"(37)","c_v1":"ﰀ"},{"id":50346,"text":"فَجُمِعَ","c_v1":"ﰁ"},{"id":50347,"text":"السَّحَرَةُ","c_v1":"ﰂ"}],"data":{}},{"words":[{"id":50348,"text":"لِمِيقَاتِ","c_v1":"ﰃ"},{"id":50349,"text":"يَوْمٍ","c_v1":"ﰄ"},{"id":50350,"text":"مَعْلُومٍ","type":"end","c_v1":"ﰅ"},{"id":50351,"text":"(38)","c_v1":"ﰆ"},{"id":50352,"text":"وَقِيلَ","c_v1":"ﰇ"},{"id":50353,"text":"لِلنَّاسِ","c_v1":"ﰈ"},{"id":50354,"text":"هَلْ","c_v1":"ﰉ"},{"id":50355,"text":"أَنْتُمْ","c_v1":"ﰊ"},{"id":50356,"text":"مُجْتَمِعُونَ","type":"end","c_v1":"ﰋ"},{"id":50357,"text":"(39)","c_v1":"ﰌ"}],"data":{}}],"header":"سُورَةُ الشُّعَرَاءِ","juz":19,"ayahs":[{"ayah":"قال فعلتها اذا وانا من الضالين","suraName":"الشعراء","ayahId":20},{"ayah":"ففررت منكم لما خفتكم فوهب لي ربي حكما وجعلني من المرسلين","suraName":"الشعراء","ayahId":21},{"ayah":"وتلك نعمة تمنها علي ان عبدت بني اسرائيل","suraName":"الشعراء","ayahId":22},{"ayah":"قال فرعون وما رب العالمين","suraName":"الشعراء","ayahId":23},{"ayah":"قال رب السماوات والارض وما بينهما ان كنتم موقنين","suraName":"الشعراء","ayahId":24},{"ayah":"قال لمن حوله الا تستمعون","suraName":"الشعراء","ayahId":25},{"ayah":"قال ربكم ورب ابائكم الاولين","suraName":"الشعراء","ayahId":26},{"ayah":"قال ان رسولكم الذي ارسل اليكم لمجنون","suraName":"الشعراء","ayahId":27},{"ayah":"قال رب المشرق والمغرب وما بينهما ان كنتم تعقلون","suraName":"الشعراء","ayahId":28},{"ayah":"قال لئن اتخذت الها غيري لاجعلنك من المسجونين","suraName":"الشعراء","ayahId":29},{"ayah":"قال اولو جئتك بشيء مبين","suraName":"الشعراء","ayahId":30},{"ayah":"قال فات به ان كنت من الصادقين","suraName":"الشعراء","ayahId":31},{"ayah":"فالقى عصاه فاذا هي ثعبان مبين","suraName":"الشعراء","ayahId":32},{"ayah":"ونزع يده فاذا هي بيضاء للناظرين","suraName":"الشعراء","ayahId":33},{"ayah":"قال للملا حوله ان هذا لساحر عليم","suraName":"الشعراء","ayahId":34},{"ayah":"يريد ان يخرجكم من ارضكم بسحره فماذا تامرون","suraName":"الشعراء","ayahId":35},{"ayah":"قالوا ارجه واخاه وابعث في المدائن حاشرين","suraName":"الشعراء","ayahId":36},{"ayah":"ياتوك بكل سحار عليم","suraName":"الشعراء","ayahId":37},{"ayah":"فجمع السحرة لميقات يوم معلوم","suraName":"الشعراء","ayahId":38},{"ayah":"وقيل للناس هل انتم مجتمعون","suraName":"الشعراء","ayahId":39}]}