{"page":564,"lines":[{"words":[{"id":78010,"text":"فَلَمَّا","c_v1":"ﭑ"},{"id":78011,"text":"رَأَوْهُ","c_v1":"ﭒ"},{"id":78012,"text":"زُلْفَةً","c_v1":"ﭓ"},{"id":78013,"text":"سِيئَتْ","c_v1":"ﭔ"},{"id":78014,"text":"وُجُوهُ","c_v1":"ﭕ"},{"id":78015,"text":"الَّذِينَ","c_v1":"ﭖ"},{"id":78016,"text":"كَفَرُوا","c_v1":"ﭗ"},{"id":78017,"text":"وَقِيلَ","c_v1":"ﭘ"},{"id":78018,"text":"هَذَا","c_v1":"ﭙ"},{"id":78019,"text":"الَّذِي","c_v1":"ﭚ"}],"data":{}},{"words":[{"id":78020,"text":"كُنْتُمْ","c_v1":"ﭛ"},{"id":78021,"text":"بِهِ","c_v1":"ﭜ"},{"id":78022,"text":"تَدَّعُونَ","c_v1":"ﭝ"},{"id":78023,"text":"(27)","type":"end","c_v1":"ﭞ"},{"id":78024,"text":"قُلْ","c_v1":"ﭟ"},{"id":78025,"text":"أَرَأَيْتُمْ","c_v1":"ﭠ"},{"id":78026,"text":"إِنْ","c_v1":"ﭡ"},{"id":78027,"text":"أَهْلَكَنِيَ","c_v1":"ﭢ"},{"id":78028,"text":"اللَّهُ","c_v1":"ﭣ"},{"id":78029,"text":"وَمَنْ","c_v1":"ﭤ"},{"id":78030,"text":"مَعِيَ","c_v1":"ﭥ"}],"data":{}},{"words":[{"id":78031,"text":"أَوْ","c_v1":"ﭦ"},{"id":78032,"text":"رَحِمَنَا","c_v1":"ﭧ"},{"id":78033,"text":"فَمَنْ","c_v1":"ﭨ"},{"id":78034,"text":"يُجِيرُ","c_v1":"ﭩ"},{"id":78035,"text":"الْكَافِرِينَ","c_v1":"ﭪ"},{"id":78036,"text":"مِنْ","c_v1":"ﭫ"},{"id":78037,"text":"عَذَابٍ","c_v1":"ﭬ"},{"id":78038,"text":"أَلِيمٍ","c_v1":"ﭭ"},{"id":78039,"text":"(28)","type":"end","c_v1":"ﭮ"},{"id":78040,"text":"قُلْ","c_v1":"ﭯ"},{"id":78041,"text":"هُوَ","c_v1":"ﭰ"}],"data":{}},{"words":[{"id":78042,"text":"الرَّحْمَنُ","c_v1":"ﭱ"},{"id":78043,"text":"آمَنَّا","c_v1":"ﭲ"},{"id":78044,"text":"بِهِ","c_v1":"ﭳ"},{"id":78045,"text":"وَعَلَيْهِ","c_v1":"ﭴ"},{"id":78046,"text":"تَوَكَّلْنَا","c_v1":"ﭵﭶ"},{"id":78047,"text":"فَسَتَعْلَمُونَ","c_v1":"ﭷ"},{"id":78048,"text":"مَنْ","c_v1":"ﭸ"},{"id":78049,"text":"هُوَ","c_v1":"ﭹ"},{"id":78050,"text":"فِي","c_v1":"ﭺ"},{"id":78051,"text":"ضَلَالٍ","c_v1":"ﭻ"},{"id":78052,"text":"مُبِينٍ","c_v1":"ﭼ"}],"data":{}},{"words":[{"id":78053,"text":"(29)","type":"end","c_v1":"ﭽ"},{"id":78054,"text":"قُلْ","c_v1":"ﭾ"},{"id":78055,"text":"أَرَأَيْتُمْ","c_v1":"ﭿ"},{"id":78056,"text":"إِنْ","c_v1":"ﮀ"},{"id":78057,"text":"أَصْبَحَ","c_v1":"ﮁ"},{"id":78058,"text":"مَاؤُكُمْ","c_v1":"ﮂ"},{"id":78059,"text":"غَوْرًا","c_v1":"ﮃ"},{"id":78060,"text":"فَمَنْ","c_v1":"ﮄ"},{"id":78061,"text":"يَأْتِيكُمْ","c_v1":"ﮅ"},{"id":78062,"text":"بِمَاءٍ","c_v1":"ﮆ"},{"id":78063,"text":"مَعِينٍ","c_v1":"ﮇ"},{"id":78064,"text":"(30)","type":"end","c_v1":"ﮈ"}],"data":{}},{"words":[],"data":{"suraName":"سُورَةُ القَلَمِ","type":"start","surahId":68}},{"words":[],"data":{"type":"besmellah"}},{"words":[{"id":78065,"text":"ن","c_v1":"ﮉﮊ"},{"id":78066,"text":"وَالْقَلَمِ","c_v1":"ﮋ"},{"id":78067,"text":"وَمَا","c_v1":"ﮌ"},{"id":78068,"text":"يَسْطُرُونَ","c_v1":"ﮍ"},{"id":78069,"text":"(1)","type":"end","c_v1":"ﮎ"},{"id":78070,"text":"مَا","c_v1":"ﮏ"},{"id":78071,"text":"أَنْتَ","c_v1":"ﮐ"},{"id":78072,"text":"بِنِعْمَةِ","c_v1":"ﮑ"},{"id":78073,"text":"رَبِّكَ","c_v1":"ﮒ"},{"id":78074,"text":"بِمَجْنُونٍ","c_v1":"ﮓ"},{"id":78075,"text":"(2)","type":"end","c_v1":"ﮔ"}],"data":{}},{"words":[{"id":78076,"text":"وَإِنَّ","c_v1":"ﮕ"},{"id":78077,"text":"لَكَ","c_v1":"ﮖ"},{"id":78078,"text":"لَأَجْرًا","c_v1":"ﮗ"},{"id":78079,"text":"غَيْرَ","c_v1":"ﮘ"},{"id":78080,"text":"مَمْنُونٍ","c_v1":"ﮙ"},{"id":78081,"text":"(3)","type":"end","c_v1":"ﮚ"},{"id":78082,"text":"وَإِنَّكَ","c_v1":"ﮛ"},{"id":78083,"text":"لَعَلَى","c_v1":"ﮜ"},{"id":78084,"text":"خُلُقٍ","c_v1":"ﮝ"},{"id":78085,"text":"عَظِيمٍ","c_v1":"ﮞ"},{"id":78086,"text":"(4)","type":"end","c_v1":"ﮟ"}],"data":{}},{"words":[{"id":78087,"text":"فَسَتُبْصِرُ","c_v1":"ﮠ"},{"id":78088,"text":"وَيُبْصِرُونَ","c_v1":"ﮡ"},{"id":78089,"text":"(5)","type":"end","c_v1":"ﮢ"},{"id":78090,"text":"بِأَيِّكُمُ","c_v1":"ﮣ"},{"id":78091,"text":"الْمَفْتُونُ","c_v1":"ﮤ"},{"id":78092,"text":"(6)","type":"end","c_v1":"ﮥ"},{"id":78093,"text":"إِنَّ","c_v1":"ﮦ"},{"id":78094,"text":"رَبَّكَ","c_v1":"ﮧ"},{"id":78095,"text":"هُوَ","c_v1":"ﮨ"}],"data":{}},{"words":[{"id":78096,"text":"أَعْلَمُ","c_v1":"ﮩ"},{"id":78097,"text":"بِمَنْ","c_v1":"ﮪ"},{"id":78098,"text":"ضَلَّ","c_v1":"ﮫ"},{"id":78099,"text":"عَنْ","c_v1":"ﮬ"},{"id":78100,"text":"سَبِيلِهِ","c_v1":"ﮭ"},{"id":78101,"text":"وَهُوَ","c_v1":"ﮮ"},{"id":78102,"text":"أَعْلَمُ","c_v1":"ﮯ"},{"id":78103,"text":"بِالْمُهْتَدِينَ","c_v1":"ﮰ"},{"id":78104,"text":"(7)","type":"end","c_v1":"ﮱ"},{"id":78105,"text":"فَلَا","c_v1":"ﯓ"},{"id":78106,"text":"تُطِعِ","c_v1":"ﯔ"}],"data":{}},{"words":[{"id":78107,"text":"الْمُكَذِّبِينَ","c_v1":"ﯕ"},{"id":78108,"text":"(8)","type":"end","c_v1":"ﯖ"},{"id":78109,"text":"وَدُّوا","c_v1":"ﯗ"},{"id":78110,"text":"لَوْ","c_v1":"ﯘ"},{"id":78111,"text":"تُدْهِنُ","c_v1":"ﯙ"},{"id":78112,"text":"فَيُدْهِنُونَ","c_v1":"ﯚ"},{"id":78113,"text":"(9)","type":"end","c_v1":"ﯛ"},{"id":78114,"text":"وَلَا","c_v1":"ﯜ"},{"id":78115,"text":"تُطِعْ","c_v1":"ﯝ"},{"id":78116,"text":"كُلَّ","c_v1":"ﯞ"}],"data":{}},{"words":[{"id":78117,"text":"حَلَّافٍ","c_v1":"ﯟ"},{"id":78118,"text":"مَهِينٍ","c_v1":"ﯠ"},{"id":78119,"text":"(10)","type":"end","c_v1":"ﯡ"},{"id":78120,"text":"هَمَّازٍ","c_v1":"ﯢ"},{"id":78121,"text":"مَشَّاءٍ","c_v1":"ﯣ"},{"id":78122,"text":"بِنَمِيمٍ","c_v1":"ﯤ"},{"id":78123,"text":"(11)","type":"end","c_v1":"ﯥ"},{"id":78124,"text":"مَنَّاعٍ","c_v1":"ﯦ"},{"id":78125,"text":"لِلْخَيْرِ","c_v1":"ﯧ"},{"id":78126,"text":"مُعْتَدٍ","c_v1":"ﯨ"}],"data":{}},{"words":[{"id":78127,"text":"أَثِيمٍ","c_v1":"ﯩ"},{"id":78128,"text":"(12)","type":"end","c_v1":"ﯪ"},{"id":78129,"text":"عُتُلٍّ","c_v1":"ﯫ"},{"id":78130,"text":"بَعْدَ","c_v1":"ﯬ"},{"id":78131,"text":"ذَلِكَ","c_v1":"ﯭ"},{"id":78132,"text":"زَنِيمٍ","c_v1":"ﯮ"},{"id":78133,"text":"(13)","type":"end","c_v1":"ﯯ"},{"id":78134,"text":"أَنْ","c_v1":"ﯰ"},{"id":78135,"text":"كَانَ","c_v1":"ﯱ"},{"id":78136,"text":"ذَا","c_v1":"ﯲ"},{"id":78137,"text":"مَالٍ","c_v1":"ﯳ"},{"id":78138,"text":"وَبَنِينَ","c_v1":"ﯴ"}],"data":{}},{"words":[{"id":78139,"text":"(14)","type":"end","c_v1":"ﯵ"},{"id":78140,"text":"إِذَا","c_v1":"ﯶ"},{"id":78141,"text":"تُتْلَى","c_v1":"ﯷ"},{"id":78142,"text":"عَلَيْهِ","c_v1":"ﯸ"},{"id":78143,"text":"آيَاتُنَا","c_v1":"ﯹ"},{"id":78144,"text":"قَالَ","c_v1":"ﯺ"},{"id":78145,"text":"أَسَاطِيرُ","c_v1":"ﯻ"},{"id":78146,"text":"الْأَوَّلِينَ","c_v1":"ﯼ"},{"id":78147,"text":"(15)","type":"end","c_v1":"ﯽ"}],"data":{}}],"header":"المُلۡكِ القَلَمِ","juz":29,"ayahs":[{"ayah":"فلما راوه زلفة سيئت وجوه الذين كفروا وقيل هذا الذي كنتم به تدعون","suraName":"الملك","ayahId":27},{"ayah":"قل ارايتم ان اهلكني الله ومن معي او رحمنا فمن يجير الكافرين من عذاب اليم","suraName":"الملك","ayahId":28},{"ayah":"قل هو الرحمن امنا به وعليه توكلنا فستعلمون من هو في ضلال مبين","suraName":"الملك","ayahId":29},{"ayah":"قل ارايتم ان اصبح ماؤكم غورا فمن ياتيكم بماء معين","suraName":"الملك","ayahId":30},{"ayah":"ن والقلم وما يسطرون","suraName":"القلم","ayahId":1},{"ayah":"ما انت بنعمة ربك بمجنون","suraName":"القلم","ayahId":2},{"ayah":"وان لك لاجرا غير ممنون","suraName":"القلم","ayahId":3},{"ayah":"وانك لعلى خلق عظيم","suraName":"القلم","ayahId":4},{"ayah":"فستبصر ويبصرون","suraName":"القلم","ayahId":5},{"ayah":"بايكم المفتون","suraName":"القلم","ayahId":6},{"ayah":"ان ربك هو اعلم بمن ضل عن سبيله وهو اعلم بالمهتدين","suraName":"القلم","ayahId":7},{"ayah":"فلا تطع المكذبين","suraName":"القلم","ayahId":8},{"ayah":"ودوا لو تدهن فيدهنون","suraName":"القلم","ayahId":9},{"ayah":"ولا تطع كل حلاف مهين","suraName":"القلم","ayahId":10},{"ayah":"هماز مشاء بنميم","suraName":"القلم","ayahId":11},{"ayah":"مناع للخير معتد اثيم","suraName":"القلم","ayahId":12},{"ayah":"عتل بعد ذلك زنيم","suraName":"القلم","ayahId":13},{"ayah":"ان كان ذا مال وبنين","suraName":"القلم","ayahId":14},{"ayah":"اذا تتلى عليه اياتنا قال اساطير الاولين","suraName":"القلم","ayahId":15}]}