{"page":345,"lines":[{"words":[{"id":46972,"text":"مَا","c_v1":"ﭑ"},{"id":46973,"text":"تَسْبِقُ","c_v1":"ﭒ"},{"id":46974,"text":"مِنْ","c_v1":"ﭓ"},{"id":46975,"text":"أُمَّةٍ","c_v1":"ﭔ"},{"id":46976,"text":"أَجَلَهَا","c_v1":"ﭕ"},{"id":46977,"text":"وَمَا","c_v1":"ﭖ"},{"id":46978,"text":"يَسْتَأْخِرُونَ","type":"end","c_v1":"ﭗ"},{"id":46979,"text":"(43)","c_v1":"ﭘ"},{"id":46980,"text":"ثُمَّ","c_v1":"ﭙ"},{"id":46981,"text":"أَرْسَلْنَا","c_v1":"ﭚ"},{"id":46982,"text":"رُسُلَنَا","c_v1":"ﭛ"},{"id":46983,"text":"تَتْرَى","c_v1":"ﭜﭝ"}],"data":{}},{"words":[{"id":46984,"text":"كُلَّ","c_v1":"ﭞ"},{"id":46985,"text":"مَا","c_v1":"ﭟ"},{"id":46986,"text":"جَاءَ","c_v1":"ﭠ"},{"id":46987,"text":"أُمَّةً","c_v1":"ﭡ"},{"id":46988,"text":"رَسُولُهَا","c_v1":"ﭢ"},{"id":46989,"text":"كَذَّبُوهُ","c_v1":"ﭣﭤ"},{"id":46990,"text":"فَأَتْبَعْنَا","c_v1":"ﭥ"},{"id":46991,"text":"بَعْضَهُمْ","c_v1":"ﭦ"},{"id":46992,"text":"بَعْضًا","c_v1":"ﭧ"},{"id":46993,"text":"وَجَعَلْنَاهُمْ","c_v1":"ﭨ"}],"data":{}},{"words":[{"id":46994,"text":"أَحَادِيثَ","c_v1":"ﭩﭪ"},{"id":46995,"text":"فَبُعْدًا","c_v1":"ﭫ"},{"id":46996,"text":"لِقَوْمٍ","c_v1":"ﭬ"},{"id":46997,"text":"لَا","c_v1":"ﭭ"},{"id":46998,"text":"يُؤْمِنُونَ","type":"end","c_v1":"ﭮ"},{"id":46999,"text":"(44)","c_v1":"ﭯ"},{"id":47000,"text":"ثُمَّ","c_v1":"ﭰ"},{"id":47001,"text":"أَرْسَلْنَا","c_v1":"ﭱ"},{"id":47002,"text":"مُوسَى","c_v1":"ﭲ"},{"id":47003,"text":"وَأَخَاهُ","c_v1":"ﭳ"}],"data":{}},{"words":[{"id":47004,"text":"هَارُونَ","c_v1":"ﭴ"},{"id":47005,"text":"بِآيَاتِنَا","c_v1":"ﭵ"},{"id":47006,"text":"وَسُلْطَانٍ","c_v1":"ﭶ"},{"id":47007,"text":"مُبِينٍ","type":"end","c_v1":"ﭷ"},{"id":47008,"text":"(45)","c_v1":"ﭸ"},{"id":47009,"text":"إِلَى","c_v1":"ﭹ"},{"id":47010,"text":"فِرْعَوْنَ","c_v1":"ﭺ"},{"id":47011,"text":"وَمَلَئِهِ","c_v1":"ﭻ"}],"data":{}},{"words":[{"id":47012,"text":"فَاسْتَكْبَرُوا","c_v1":"ﭼ"},{"id":47013,"text":"وَكَانُوا","c_v1":"ﭽ"},{"id":47014,"text":"قَوْمًا","c_v1":"ﭾ"},{"id":47015,"text":"عَالِينَ","type":"end","c_v1":"ﭿ"},{"id":47016,"text":"(46)","c_v1":"ﮀ"},{"id":47017,"text":"فَقَالُوا","c_v1":"ﮁ"},{"id":47018,"text":"أَنُؤْمِنُ","c_v1":"ﮂ"},{"id":47019,"text":"لِبَشَرَيْنِ","c_v1":"ﮃ"},{"id":47020,"text":"مِثْلِنَا","c_v1":"ﮄ"}],"data":{}},{"words":[{"id":47021,"text":"وَقَوْمُهُمَا","c_v1":"ﮅ"},{"id":47022,"text":"لَنَا","c_v1":"ﮆ"},{"id":47023,"text":"عَابِدُونَ","type":"end","c_v1":"ﮇ"},{"id":47024,"text":"(47)","c_v1":"ﮈ"},{"id":47025,"text":"فَكَذَّبُوهُمَا","c_v1":"ﮉ"},{"id":47026,"text":"فَكَانُوا","c_v1":"ﮊ"},{"id":47027,"text":"مِنَ","c_v1":"ﮋ"},{"id":47028,"text":"الْمُهْلَكِينَ","type":"end","c_v1":"ﮌ"}],"data":{}},{"words":[{"id":47029,"text":"(48)","c_v1":"ﮍ"},{"id":47030,"text":"وَلَقَدْ","c_v1":"ﮎ"},{"id":47031,"text":"آتَيْنَا","c_v1":"ﮏ"},{"id":47032,"text":"مُوسَى","c_v1":"ﮐ"},{"id":47033,"text":"الْكِتَابَ","c_v1":"ﮑ"},{"id":47034,"text":"لَعَلَّهُمْ","c_v1":"ﮒ"},{"id":47035,"text":"يَهْتَدُونَ","type":"end","c_v1":"ﮓ"},{"id":47036,"text":"(49)","c_v1":"ﮔ"},{"id":47037,"text":"وَجَعَلْنَا","c_v1":"ﮕ"}],"data":{}},{"words":[{"id":47038,"text":"ابْنَ","c_v1":"ﮖ"},{"id":47039,"text":"مَرْيَمَ","c_v1":"ﮗ"},{"id":47040,"text":"وَأُمَّهُ","c_v1":"ﮘ"},{"id":47041,"text":"آيَةً","c_v1":"ﮙ"},{"id":47042,"text":"وَآوَيْنَاهُمَا","c_v1":"ﮚ"},{"id":47043,"text":"إِلَى","c_v1":"ﮛ"},{"id":47044,"text":"رَبْوَةٍ","c_v1":"ﮜ"},{"id":47045,"text":"ذَاتِ","c_v1":"ﮝ"},{"id":47046,"text":"قَرَارٍ","c_v1":"ﮞ"},{"id":47047,"text":"وَمَعِينٍ","type":"end","c_v1":"ﮟ"}],"data":{}},{"words":[{"id":47048,"text":"(50)","c_v1":"ﮠ"},{"id":47049,"text":"يَاأَيُّهَا","c_v1":"ﮡ"},{"id":47050,"text":"الرُّسُلُ","c_v1":"ﮢ"},{"id":47051,"text":"كُلُوا","c_v1":"ﮣ"},{"id":47052,"text":"مِنَ","c_v1":"ﮤ"},{"id":47053,"text":"الطَّيِّبَاتِ","c_v1":"ﮥ"},{"id":47054,"text":"وَاعْمَلُوا","c_v1":"ﮦ"},{"id":47055,"text":"صَالِحًا","c_v1":"ﮧﮨ"},{"id":47056,"text":"إِنِّي","c_v1":"ﮩ"},{"id":47057,"text":"بِمَا","c_v1":"ﮪ"}],"data":{}},{"words":[{"id":47058,"text":"تَعْمَلُونَ","c_v1":"ﮫ"},{"id":47059,"text":"عَلِيمٌ","type":"end","c_v1":"ﮬ"},{"id":47060,"text":"(51)","c_v1":"ﮭ"},{"id":47061,"text":"وَإِنَّ","c_v1":"ﮮ"},{"id":47062,"text":"هَذِهِ","c_v1":"ﮯ"},{"id":47063,"text":"أُمَّتُكُمْ","c_v1":"ﮰ"},{"id":47064,"text":"أُمَّةً","c_v1":"ﮱ"},{"id":47065,"text":"وَاحِدَةً","c_v1":"ﯓ"},{"id":47066,"text":"وَأَنَا","c_v1":"ﯔ"},{"id":47067,"text":"رَبُّكُمْ","c_v1":"ﯕ"}],"data":{}},{"words":[{"id":47068,"text":"فَاتَّقُونِ","type":"end","c_v1":"ﯖ"},{"id":47069,"text":"(52)","c_v1":"ﯗ"},{"id":47070,"text":"فَتَقَطَّعُوا","c_v1":"ﯘ"},{"id":47071,"text":"أَمْرَهُمْ","c_v1":"ﯙ"},{"id":47072,"text":"بَيْنَهُمْ","c_v1":"ﯚ"},{"id":47073,"text":"زُبُرًا","c_v1":"ﯛﯜ"},{"id":47074,"text":"كُلُّ","c_v1":"ﯝ"},{"id":47075,"text":"حِزْبٍ","c_v1":"ﯞ"},{"id":47076,"text":"بِمَا","c_v1":"ﯟ"},{"id":47077,"text":"لَدَيْهِمْ","c_v1":"ﯠ"}],"data":{}},{"words":[{"id":47078,"text":"فَرِحُونَ","type":"end","c_v1":"ﯡ"},{"id":47079,"text":"(53)","c_v1":"ﯢ"},{"id":47080,"text":"فَذَرْهُمْ","c_v1":"ﯣ"},{"id":47081,"text":"فِي","c_v1":"ﯤ"},{"id":47082,"text":"غَمْرَتِهِمْ","c_v1":"ﯥ"},{"id":47083,"text":"حَتَّى","c_v1":"ﯦ"},{"id":47084,"text":"حِينٍ","type":"end","c_v1":"ﯧ"},{"id":47085,"text":"(54)","c_v1":"ﯨ"},{"id":47086,"text":"أَيَحْسَبُونَ","c_v1":"ﯩ"},{"id":47087,"text":"أَنَّمَا","c_v1":"ﯪ"}],"data":{}},{"words":[{"id":47088,"text":"نُمِدُّهُمْ","c_v1":"ﯫ"},{"id":47089,"text":"بِهِ","c_v1":"ﯬ"},{"id":47090,"text":"مِنْ","c_v1":"ﯭ"},{"id":47091,"text":"مَالٍ","c_v1":"ﯮ"},{"id":47092,"text":"وَبَنِينَ","type":"end","c_v1":"ﯯ"},{"id":47093,"text":"(55)","c_v1":"ﯰ"},{"id":47094,"text":"نُسَارِعُ","c_v1":"ﯱ"},{"id":47095,"text":"لَهُمْ","c_v1":"ﯲ"},{"id":47096,"text":"فِي","c_v1":"ﯳ"},{"id":47097,"text":"الْخَيْرَاتِ","c_v1":"ﯴﯵ"},{"id":47098,"text":"بَلْ","c_v1":"ﯶ"},{"id":47099,"text":"لَا","c_v1":"ﯷ"},{"id":47100,"text":"يَشْعُرُونَ","type":"end","c_v1":"ﯸ"}],"data":{}},{"words":[{"id":47101,"text":"(56)","c_v1":"ﯹ"},{"id":47102,"text":"إِنَّ","c_v1":"ﯺ"},{"id":47103,"text":"الَّذِينَ","c_v1":"ﯻ"},{"id":47104,"text":"هُمْ","c_v1":"ﯼ"},{"id":47105,"text":"مِنْ","c_v1":"ﯽ"},{"id":47106,"text":"خَشْيَةِ","c_v1":"ﯾ"},{"id":47107,"text":"رَبِّهِمْ","c_v1":"ﯿ"},{"id":47108,"text":"مُشْفِقُونَ","type":"end","c_v1":"ﰀ"},{"id":47109,"text":"(57)","c_v1":"ﰁ"},{"id":47110,"text":"وَالَّذِينَ","c_v1":"ﰂ"},{"id":47111,"text":"هُمْ","c_v1":"ﰃ"}],"data":{}},{"words":[{"id":47112,"text":"بِآيَاتِ","c_v1":"ﰄ"},{"id":47113,"text":"رَبِّهِمْ","c_v1":"ﰅ"},{"id":47114,"text":"يُؤْمِنُونَ","type":"end","c_v1":"ﰆ"},{"id":47115,"text":"(58)","c_v1":"ﰇ"},{"id":47116,"text":"وَالَّذِينَ","c_v1":"ﰈ"},{"id":47117,"text":"هُمْ","c_v1":"ﰉ"},{"id":47118,"text":"بِرَبِّهِمْ","c_v1":"ﰊ"},{"id":47119,"text":"لَا","c_v1":"ﰋ"},{"id":47120,"text":"يُشْرِكُونَ","type":"end","c_v1":"ﰌ"},{"id":47121,"text":"(59)","c_v1":"ﰍ"}],"data":{}}],"header":"سُورَةُ المُؤۡمِنُونَ","juz":18,"ayahs":[{"ayah":"ما تسبق من امة اجلها وما يستاخرون","suraName":"المؤمنون","ayahId":43},{"ayah":"ثم ارسلنا رسلنا تترى كل ما جاء امة رسولها كذبوه فاتبعنا بعضهم بعضا وجعلناهم احاديث فبعدا لقوم لا يؤمنون","suraName":"المؤمنون","ayahId":44},{"ayah":"ثم ارسلنا موسى واخاه هارون باياتنا وسلطان مبين","suraName":"المؤمنون","ayahId":45},{"ayah":"الى فرعون وملئه فاستكبروا وكانوا قوما عالين","suraName":"المؤمنون","ayahId":46},{"ayah":"فقالوا انؤمن لبشرين مثلنا وقومهما لنا عابدون","suraName":"المؤمنون","ayahId":47},{"ayah":"فكذبوهما فكانوا من المهلكين","suraName":"المؤمنون","ayahId":48},{"ayah":"ولقد اتينا موسى الكتاب لعلهم يهتدون","suraName":"المؤمنون","ayahId":49},{"ayah":"وجعلنا ابن مريم وامه اية واويناهما الى ربوة ذات قرار ومعين","suraName":"المؤمنون","ayahId":50},{"ayah":"ياايها الرسل كلوا من الطيبات واعملوا صالحا اني بما تعملون عليم","suraName":"المؤمنون","ayahId":51},{"ayah":"وان هذه امتكم امة واحدة وانا ربكم فاتقون","suraName":"المؤمنون","ayahId":52},{"ayah":"فتقطعوا امرهم بينهم زبرا كل حزب بما لديهم فرحون","suraName":"المؤمنون","ayahId":53},{"ayah":"فذرهم في غمرتهم حتى حين","suraName":"المؤمنون","ayahId":54},{"ayah":"ايحسبون انما نمدهم به من مال وبنين","suraName":"المؤمنون","ayahId":55},{"ayah":"نسارع لهم في الخيرات بل لا يشعرون","suraName":"المؤمنون","ayahId":56},{"ayah":"ان الذين هم من خشية ربهم مشفقون","suraName":"المؤمنون","ayahId":57},{"ayah":"والذين هم بايات ربهم يؤمنون","suraName":"المؤمنون","ayahId":58},{"ayah":"والذين هم بربهم لا يشركون","suraName":"المؤمنون","ayahId":59}]}