{"page":371,"lines":[{"words":[{"id":50662,"text":"وَاجْعَلْ","c_v1":"ﭑ"},{"id":50663,"text":"لِي","c_v1":"ﭒ"},{"id":50664,"text":"لِسَانَ","c_v1":"ﭓ"},{"id":50665,"text":"صِدْقٍ","c_v1":"ﭔ"},{"id":50666,"text":"فِي","c_v1":"ﭕ"},{"id":50667,"text":"الْآخِرِينَ","type":"end","c_v1":"ﭖ"},{"id":50668,"text":"(84)","c_v1":"ﭗ"},{"id":50669,"text":"وَاجْعَلْنِي","c_v1":"ﭘ"},{"id":50670,"text":"مِنْ","c_v1":"ﭙ"},{"id":50671,"text":"وَرَثَةِ","c_v1":"ﭚ"},{"id":50672,"text":"جَنَّةِ","c_v1":"ﭛ"}],"data":{}},{"words":[{"id":50673,"text":"النَّعِيمِ","type":"end","c_v1":"ﭜ"},{"id":50674,"text":"(85)","c_v1":"ﭝ"},{"id":50675,"text":"وَاغْفِرْ","c_v1":"ﭞ"},{"id":50676,"text":"لِأَبِي","c_v1":"ﭟ"},{"id":50677,"text":"إِنَّهُ","c_v1":"ﭠ"},{"id":50678,"text":"كَانَ","c_v1":"ﭡ"},{"id":50679,"text":"مِنَ","c_v1":"ﭢ"},{"id":50680,"text":"الضَّالِّينَ","type":"end","c_v1":"ﭣ"},{"id":50681,"text":"(86)","c_v1":"ﭤ"},{"id":50682,"text":"وَلَا","c_v1":"ﭥ"},{"id":50683,"text":"تُخْزِنِي","c_v1":"ﭦ"},{"id":50684,"text":"يَوْمَ","c_v1":"ﭧ"}],"data":{}},{"words":[{"id":50685,"text":"يُبْعَثُونَ","type":"end","c_v1":"ﭨ"},{"id":50686,"text":"(87)","c_v1":"ﭩ"},{"id":50687,"text":"يَوْمَ","c_v1":"ﭪ"},{"id":50688,"text":"لَا","c_v1":"ﭫ"},{"id":50689,"text":"يَنْفَعُ","c_v1":"ﭬ"},{"id":50690,"text":"مَالٌ","c_v1":"ﭭ"},{"id":50691,"text":"وَلَا","c_v1":"ﭮ"},{"id":50692,"text":"بَنُونَ","type":"end","c_v1":"ﭯ"},{"id":50693,"text":"(88)","c_v1":"ﭰ"},{"id":50694,"text":"إِلَّا","c_v1":"ﭱ"},{"id":50695,"text":"مَنْ","c_v1":"ﭲ"},{"id":50696,"text":"أَتَى","c_v1":"ﭳ"},{"id":50697,"text":"اللَّهَ","c_v1":"ﭴ"},{"id":50698,"text":"بِقَلْبٍ","c_v1":"ﭵ"}],"data":{}},{"words":[{"id":50699,"text":"سَلِيمٍ","type":"end","c_v1":"ﭶ"},{"id":50700,"text":"(89)","c_v1":"ﭷ"},{"id":50701,"text":"وَأُزْلِفَتِ","c_v1":"ﭸ"},{"id":50702,"text":"الْجَنَّةُ","c_v1":"ﭹ"},{"id":50703,"text":"لِلْمُتَّقِينَ","type":"end","c_v1":"ﭺ"},{"id":50704,"text":"(90)","c_v1":"ﭻ"},{"id":50705,"text":"وَبُرِّزَتِ","c_v1":"ﭼ"},{"id":50706,"text":"الْجَحِيمُ","c_v1":"ﭽ"},{"id":50707,"text":"لِلْغَاوِينَ","type":"end","c_v1":"ﭾ"}],"data":{}},{"words":[{"id":50708,"text":"(91)","c_v1":"ﭿ"},{"id":50709,"text":"وَقِيلَ","c_v1":"ﮀ"},{"id":50710,"text":"لَهُمْ","c_v1":"ﮁ"},{"id":50711,"text":"أَيْنَ","c_v1":"ﮂ"},{"id":50712,"text":"مَا","c_v1":"ﮃ"},{"id":50713,"text":"كُنْتُمْ","c_v1":"ﮄ"},{"id":50714,"text":"تَعْبُدُونَ","type":"end","c_v1":"ﮅ"},{"id":50715,"text":"(92)","c_v1":"ﮆ"},{"id":50716,"text":"مِنْ","c_v1":"ﮇ"},{"id":50717,"text":"دُونِ","c_v1":"ﮈ"},{"id":50718,"text":"اللَّهِ","c_v1":"ﮉ"},{"id":50719,"text":"هَلْ","c_v1":"ﮊ"},{"id":50720,"text":"يَنْصُرُونَكُمْ","c_v1":"ﮋ"}],"data":{}},{"words":[{"id":50721,"text":"أَوْ","c_v1":"ﮌ"},{"id":50722,"text":"يَنْتَصِرُونَ","type":"end","c_v1":"ﮍ"},{"id":50723,"text":"(93)","c_v1":"ﮎ"},{"id":50724,"text":"فَكُبْكِبُوا","c_v1":"ﮏ"},{"id":50725,"text":"فِيهَا","c_v1":"ﮐ"},{"id":50726,"text":"هُمْ","c_v1":"ﮑ"},{"id":50727,"text":"وَالْغَاوُونَ","type":"end","c_v1":"ﮒ"},{"id":50728,"text":"(94)","c_v1":"ﮓ"},{"id":50729,"text":"وَجُنُودُ","c_v1":"ﮔ"},{"id":50730,"text":"إِبْلِيسَ","c_v1":"ﮕ"}],"data":{}},{"words":[{"id":50731,"text":"أَجْمَعُونَ","type":"end","c_v1":"ﮖ"},{"id":50732,"text":"(95)","c_v1":"ﮗ"},{"id":50733,"text":"قَالُوا","c_v1":"ﮘ"},{"id":50734,"text":"وَهُمْ","c_v1":"ﮙ"},{"id":50735,"text":"فِيهَا","c_v1":"ﮚ"},{"id":50736,"text":"يَخْتَصِمُونَ","type":"end","c_v1":"ﮛ"},{"id":50737,"text":"(96)","c_v1":"ﮜ"},{"id":50738,"text":"تَاللَّهِ","c_v1":"ﮝ"},{"id":50739,"text":"إِنْ","c_v1":"ﮞ"},{"id":50740,"text":"كُنَّا","c_v1":"ﮟ"},{"id":50741,"text":"لَفِي","c_v1":"ﮠ"}],"data":{}},{"words":[{"id":50742,"text":"ضَلَالٍ","c_v1":"ﮡ"},{"id":50743,"text":"مُبِينٍ","type":"end","c_v1":"ﮢ"},{"id":50744,"text":"(97)","c_v1":"ﮣ"},{"id":50745,"text":"إِذْ","c_v1":"ﮤ"},{"id":50746,"text":"نُسَوِّيكُمْ","c_v1":"ﮥ"},{"id":50747,"text":"بِرَبِّ","c_v1":"ﮦ"},{"id":50748,"text":"الْعَالَمِينَ","type":"end","c_v1":"ﮧ"},{"id":50749,"text":"(98)","c_v1":"ﮨ"},{"id":50750,"text":"وَمَا","c_v1":"ﮩ"},{"id":50751,"text":"أَضَلَّنَا","c_v1":"ﮪ"}],"data":{}},{"words":[{"id":50752,"text":"إِلَّا","c_v1":"ﮫ"},{"id":50753,"text":"الْمُجْرِمُونَ","type":"end","c_v1":"ﮬ"},{"id":50754,"text":"(99)","c_v1":"ﮭ"},{"id":50755,"text":"فَمَا","c_v1":"ﮮ"},{"id":50756,"text":"لَنَا","c_v1":"ﮯ"},{"id":50757,"text":"مِنْ","c_v1":"ﮰ"},{"id":50758,"text":"شَافِعِينَ","type":"end","c_v1":"ﮱ"},{"id":50759,"text":"(100)","c_v1":"ﯓ"},{"id":50760,"text":"وَلَا","c_v1":"ﯔ"},{"id":50761,"text":"صَدِيقٍ","c_v1":"ﯕ"},{"id":50762,"text":"حَمِيمٍ","type":"end","c_v1":"ﯖ"},{"id":50763,"text":"(101)","c_v1":"ﯗ"}],"data":{}},{"words":[{"id":50764,"text":"فَلَوْ","c_v1":"ﯘ"},{"id":50765,"text":"أَنَّ","c_v1":"ﯙ"},{"id":50766,"text":"لَنَا","c_v1":"ﯚ"},{"id":50767,"text":"كَرَّةً","c_v1":"ﯛ"},{"id":50768,"text":"فَنَكُونَ","c_v1":"ﯜ"},{"id":50769,"text":"مِنَ","c_v1":"ﯝ"},{"id":50770,"text":"الْمُؤْمِنِينَ","type":"end","c_v1":"ﯞ"},{"id":50771,"text":"(102)","c_v1":"ﯟ"},{"id":50772,"text":"إِنَّ","c_v1":"ﯠ"},{"id":50773,"text":"فِي","c_v1":"ﯡ"},{"id":50774,"text":"ذَلِكَ","c_v1":"ﯢ"},{"id":50775,"text":"لَآيَةً","c_v1":"ﯣﯤ"},{"id":50776,"text":"وَمَا","c_v1":"ﯥ"},{"id":50777,"text":"كَانَ","c_v1":"ﯦ"}],"data":{}},{"words":[{"id":50778,"text":"أَكْثَرُهُمْ","c_v1":"ﯧ"},{"id":50779,"text":"مُؤْمِنِينَ","type":"end","c_v1":"ﯨ"},{"id":50780,"text":"(103)","c_v1":"ﯩ"},{"id":50781,"text":"وَإِنَّ","c_v1":"ﯪ"},{"id":50782,"text":"رَبَّكَ","c_v1":"ﯫ"},{"id":50783,"text":"لَهُوَ","c_v1":"ﯬ"},{"id":50784,"text":"الْعَزِيزُ","c_v1":"ﯭ"},{"id":50785,"text":"الرَّحِيمُ","type":"end","c_v1":"ﯮ"},{"id":50786,"text":"(104)","c_v1":"ﯯ"},{"id":50787,"text":"كَذَّبَتْ","c_v1":"ﯰ"}],"data":{}},{"words":[{"id":50788,"text":"قَوْمُ","c_v1":"ﯱ"},{"id":50789,"text":"نُوحٍ","c_v1":"ﯲ"},{"id":50790,"text":"الْمُرْسَلِينَ","type":"end","c_v1":"ﯳ"},{"id":50791,"text":"(105)","c_v1":"ﯴ"},{"id":50792,"text":"إِذْ","c_v1":"ﯵ"},{"id":50793,"text":"قَالَ","c_v1":"ﯶ"},{"id":50794,"text":"لَهُمْ","c_v1":"ﯷ"},{"id":50795,"text":"أَخُوهُمْ","c_v1":"ﯸ"},{"id":50796,"text":"نُوحٌ","c_v1":"ﯹ"},{"id":50797,"text":"أَلَا","c_v1":"ﯺ"},{"id":50798,"text":"تَتَّقُونَ","type":"end","c_v1":"ﯻ"},{"id":50799,"text":"(106)","c_v1":"ﯼ"}],"data":{}},{"words":[{"id":50800,"text":"إِنِّي","c_v1":"ﯽ"},{"id":50801,"text":"لَكُمْ","c_v1":"ﯾ"},{"id":50802,"text":"رَسُولٌ","c_v1":"ﯿ"},{"id":50803,"text":"أَمِينٌ","type":"end","c_v1":"ﰀ"},{"id":50804,"text":"(107)","c_v1":"ﰁ"},{"id":50805,"text":"فَاتَّقُوا","c_v1":"ﰂ"},{"id":50806,"text":"اللَّهَ","c_v1":"ﰃ"},{"id":50807,"text":"وَأَطِيعُونِ","type":"end","c_v1":"ﰄ"},{"id":50808,"text":"(108)","c_v1":"ﰅ"},{"id":50809,"text":"وَمَا","c_v1":"ﰆ"},{"id":50810,"text":"أَسْأَلُكُمْ","c_v1":"ﰇ"}],"data":{}},{"words":[{"id":50811,"text":"عَلَيْهِ","c_v1":"ﰈ"},{"id":50812,"text":"مِنْ","c_v1":"ﰉ"},{"id":50813,"text":"أَجْرٍ","c_v1":"ﰊﰋ"},{"id":50814,"text":"إِنْ","c_v1":"ﰌ"},{"id":50815,"text":"أَجْرِيَ","c_v1":"ﰍ"},{"id":50816,"text":"إِلَّا","c_v1":"ﰎ"},{"id":50817,"text":"عَلَى","c_v1":"ﰏ"},{"id":50818,"text":"رَبِّ","c_v1":"ﰐ"},{"id":50819,"text":"الْعَالَمِينَ","type":"end","c_v1":"ﰑ"},{"id":50820,"text":"(109)","c_v1":"ﰒ"},{"id":50821,"text":"فَاتَّقُوا","c_v1":"ﰓ"},{"id":50822,"text":"اللَّهَ","c_v1":"ﰔ"}],"data":{}},{"words":[{"id":50823,"text":"وَأَطِيعُونِ","type":"end","c_v1":"ﰕ"},{"id":50824,"text":"(110)","c_v1":"ﰖ"},{"id":50825,"text":"قَالُوا","c_v1":"ﰗ ﰘ"},{"id":50826,"text":"أَنُؤْمِنُ","c_v1":"ﰙ"},{"id":50827,"text":"لَكَ","c_v1":"ﰚ"},{"id":50828,"text":"وَاتَّبَعَكَ","c_v1":"ﰛ"},{"id":50829,"text":"الْأَرْذَلُونَ","type":"end","c_v1":"ﰜ"},{"id":50830,"text":"(111)","c_v1":"ﰝ"}],"data":{}}],"header":"سُورَةُ الشُّعَرَاءِ","juz":19,"ayahs":[{"ayah":"واجعل لي لسان صدق في الاخرين","suraName":"الشعراء","ayahId":84},{"ayah":"واجعلني من ورثة جنة النعيم","suraName":"الشعراء","ayahId":85},{"ayah":"واغفر لابي انه كان من الضالين","suraName":"الشعراء","ayahId":86},{"ayah":"ولا تخزني يوم يبعثون","suraName":"الشعراء","ayahId":87},{"ayah":"يوم لا ينفع مال ولا بنون","suraName":"الشعراء","ayahId":88},{"ayah":"الا من اتى الله بقلب سليم","suraName":"الشعراء","ayahId":89},{"ayah":"وازلفت الجنة للمتقين","suraName":"الشعراء","ayahId":90},{"ayah":"وبرزت الجحيم للغاوين","suraName":"الشعراء","ayahId":91},{"ayah":"وقيل لهم اين ما كنتم تعبدون","suraName":"الشعراء","ayahId":92},{"ayah":"من دون الله هل ينصرونكم او ينتصرون","suraName":"الشعراء","ayahId":93},{"ayah":"فكبكبوا فيها هم والغاوون","suraName":"الشعراء","ayahId":94},{"ayah":"وجنود ابليس اجمعون","suraName":"الشعراء","ayahId":95},{"ayah":"قالوا وهم فيها يختصمون","suraName":"الشعراء","ayahId":96},{"ayah":"تالله ان كنا لفي ضلال مبين","suraName":"الشعراء","ayahId":97},{"ayah":"اذ نسويكم برب العالمين","suraName":"الشعراء","ayahId":98},{"ayah":"وما اضلنا الا المجرمون","suraName":"الشعراء","ayahId":99},{"ayah":"فما لنا من شافعين","suraName":"الشعراء","ayahId":100},{"ayah":"ولا صديق حميم","suraName":"الشعراء","ayahId":101},{"ayah":"فلو ان لنا كرة فنكون من المؤمنين","suraName":"الشعراء","ayahId":102},{"ayah":"ان في ذلك لاية وما كان اكثرهم مؤمنين","suraName":"الشعراء","ayahId":103},{"ayah":"وان ربك لهو العزيز الرحيم","suraName":"الشعراء","ayahId":104},{"ayah":"كذبت قوم نوح المرسلين","suraName":"الشعراء","ayahId":105},{"ayah":"اذ قال لهم اخوهم نوح الا تتقون","suraName":"الشعراء","ayahId":106},{"ayah":"اني لكم رسول امين","suraName":"الشعراء","ayahId":107},{"ayah":"فاتقوا الله واطيعون","suraName":"الشعراء","ayahId":108},{"ayah":"وما اسالكم عليه من اجر ان اجري الا على رب العالمين","suraName":"الشعراء","ayahId":109},{"ayah":"فاتقوا الله واطيعون","suraName":"الشعراء","ayahId":110},{"ayah":"قالوا انؤمن لك واتبعك الارذلون","suraName":"الشعراء","ayahId":111}]}