{"page":448,"lines":[{"words":[{"id":61500,"text":"يَقُولُ","c_v1":"ﭑ"},{"id":61501,"text":"أَإِنَّكَ","c_v1":"ﭒ"},{"id":61502,"text":"لَمِنَ","c_v1":"ﭓ"},{"id":61503,"text":"الْمُصَدِّقِينَ","type":"end","c_v1":"ﭔ"},{"id":61504,"text":"(52)","c_v1":"ﭕ"},{"id":61505,"text":"أَإِذَا","c_v1":"ﭖ"},{"id":61506,"text":"مِتْنَا","c_v1":"ﭗ"},{"id":61507,"text":"وَكُنَّا","c_v1":"ﭘ"},{"id":61508,"text":"تُرَابًا","c_v1":"ﭙ"},{"id":61509,"text":"وَعِظَامًا","c_v1":"ﭚ"},{"id":61510,"text":"أَإِنَّا","c_v1":"ﭛ"}],"data":{}},{"words":[{"id":61511,"text":"لَمَدِينُونَ","type":"end","c_v1":"ﭜ"},{"id":61512,"text":"(53)","c_v1":"ﭝ"},{"id":61513,"text":"قَالَ","c_v1":"ﭞ"},{"id":61514,"text":"هَلْ","c_v1":"ﭟ"},{"id":61515,"text":"أَنْتُمْ","c_v1":"ﭠ"},{"id":61516,"text":"مُطَّلِعُونَ","type":"end","c_v1":"ﭡ"},{"id":61517,"text":"(54)","c_v1":"ﭢ"},{"id":61518,"text":"فَاطَّلَعَ","c_v1":"ﭣ"},{"id":61519,"text":"فَرَآهُ","c_v1":"ﭤ"},{"id":61520,"text":"فِي","c_v1":"ﭥ"},{"id":61521,"text":"سَوَاءِ","c_v1":"ﭦ"}],"data":{}},{"words":[{"id":61522,"text":"الْجَحِيمِ","type":"end","c_v1":"ﭧ"},{"id":61523,"text":"(55)","c_v1":"ﭨ"},{"id":61524,"text":"قَالَ","c_v1":"ﭩ"},{"id":61525,"text":"تَاللَّهِ","c_v1":"ﭪ"},{"id":61526,"text":"إِنْ","c_v1":"ﭫ"},{"id":61527,"text":"كِدْتَ","c_v1":"ﭬ"},{"id":61528,"text":"لَتُرْدِينِ","type":"end","c_v1":"ﭭ"},{"id":61529,"text":"(56)","c_v1":"ﭮ"},{"id":61530,"text":"وَلَوْلَا","c_v1":"ﭯ"},{"id":61531,"text":"نِعْمَةُ","c_v1":"ﭰ"},{"id":61532,"text":"رَبِّي","c_v1":"ﭱ"}],"data":{}},{"words":[{"id":61533,"text":"لَكُنْتُ","c_v1":"ﭲ"},{"id":61534,"text":"مِنَ","c_v1":"ﭳ"},{"id":61535,"text":"الْمُحْضَرِينَ","type":"end","c_v1":"ﭴ"},{"id":61536,"text":"(57)","c_v1":"ﭵ"},{"id":61537,"text":"أَفَمَا","c_v1":"ﭶ"},{"id":61538,"text":"نَحْنُ","c_v1":"ﭷ"},{"id":61539,"text":"بِمَيِّتِينَ","type":"end","c_v1":"ﭸ"},{"id":61540,"text":"(58)","c_v1":"ﭹ"},{"id":61541,"text":"إِلَّا","c_v1":"ﭺ"},{"id":61542,"text":"مَوْتَتَنَا","c_v1":"ﭻ"}],"data":{}},{"words":[{"id":61543,"text":"الْأُولَى","c_v1":"ﭼ"},{"id":61544,"text":"وَمَا","c_v1":"ﭽ"},{"id":61545,"text":"نَحْنُ","c_v1":"ﭾ"},{"id":61546,"text":"بِمُعَذَّبِينَ","type":"end","c_v1":"ﭿ"},{"id":61547,"text":"(59)","c_v1":"ﮀ"},{"id":61548,"text":"إِنَّ","c_v1":"ﮁ"},{"id":61549,"text":"هَذَا","c_v1":"ﮂ"},{"id":61550,"text":"لَهُوَ","c_v1":"ﮃ"},{"id":61551,"text":"الْفَوْزُ","c_v1":"ﮄ"},{"id":61552,"text":"الْعَظِيمُ","type":"end","c_v1":"ﮅ"},{"id":61553,"text":"(60)","c_v1":"ﮆ"}],"data":{}},{"words":[{"id":61554,"text":"لِمِثْلِ","c_v1":"ﮇ"},{"id":61555,"text":"هَذَا","c_v1":"ﮈ"},{"id":61556,"text":"فَلْيَعْمَلِ","c_v1":"ﮉ"},{"id":61557,"text":"الْعَامِلُونَ","type":"end","c_v1":"ﮊ"},{"id":61558,"text":"(61)","c_v1":"ﮋ"},{"id":61559,"text":"أَذَلِكَ","c_v1":"ﮌ"},{"id":61560,"text":"خَيْرٌ","c_v1":"ﮍ"},{"id":61561,"text":"نُزُلًا","c_v1":"ﮎ"},{"id":61562,"text":"أَمْ","c_v1":"ﮏ"},{"id":61563,"text":"شَجَرَةُ","c_v1":"ﮐ"}],"data":{}},{"words":[{"id":61564,"text":"الزَّقُّومِ","type":"end","c_v1":"ﮑ"},{"id":61565,"text":"(62)","c_v1":"ﮒ"},{"id":61566,"text":"إِنَّا","c_v1":"ﮓ"},{"id":61567,"text":"جَعَلْنَاهَا","c_v1":"ﮔ"},{"id":61568,"text":"فِتْنَةً","c_v1":"ﮕ"},{"id":61569,"text":"لِلظَّالِمِينَ","type":"end","c_v1":"ﮖ"},{"id":61570,"text":"(63)","c_v1":"ﮗ"},{"id":61571,"text":"إِنَّهَا","c_v1":"ﮘ"},{"id":61572,"text":"شَجَرَةٌ","c_v1":"ﮙ"}],"data":{}},{"words":[{"id":61573,"text":"تَخْرُجُ","c_v1":"ﮚ"},{"id":61574,"text":"فِي","c_v1":"ﮛ"},{"id":61575,"text":"أَصْلِ","c_v1":"ﮜ"},{"id":61576,"text":"الْجَحِيمِ","type":"end","c_v1":"ﮝ"},{"id":61577,"text":"(64)","c_v1":"ﮞ"},{"id":61578,"text":"طَلْعُهَا","c_v1":"ﮟ"},{"id":61579,"text":"كَأَنَّهُ","c_v1":"ﮠ"},{"id":61580,"text":"رُءُوسُ","c_v1":"ﮡ"},{"id":61581,"text":"الشَّيَاطِينِ","type":"end","c_v1":"ﮢ"}],"data":{}},{"words":[{"id":61582,"text":"(65)","c_v1":"ﮣ"},{"id":61583,"text":"فَإِنَّهُمْ","c_v1":"ﮤ"},{"id":61584,"text":"لَآكِلُونَ","c_v1":"ﮥ"},{"id":61585,"text":"مِنْهَا","c_v1":"ﮦ"},{"id":61586,"text":"فَمَالِئُونَ","c_v1":"ﮧ"},{"id":61587,"text":"مِنْهَا","c_v1":"ﮨ"},{"id":61588,"text":"الْبُطُونَ","type":"end","c_v1":"ﮩ"},{"id":61589,"text":"(66)","c_v1":"ﮪ"},{"id":61590,"text":"ثُمَّ","c_v1":"ﮫ"},{"id":61591,"text":"إِنَّ","c_v1":"ﮬ"},{"id":61592,"text":"لَهُمْ","c_v1":"ﮭ"}],"data":{}},{"words":[{"id":61593,"text":"عَلَيْهَا","c_v1":"ﮮ"},{"id":61594,"text":"لَشَوْبًا","c_v1":"ﮯ"},{"id":61595,"text":"مِنْ","c_v1":"ﮰ"},{"id":61596,"text":"حَمِيمٍ","type":"end","c_v1":"ﮱ"},{"id":61597,"text":"(67)","c_v1":"ﯓ"},{"id":61598,"text":"ثُمَّ","c_v1":"ﯔ"},{"id":61599,"text":"إِنَّ","c_v1":"ﯕ"},{"id":61600,"text":"مَرْجِعَهُمْ","c_v1":"ﯖ"},{"id":61601,"text":"لَإِلَى","c_v1":"ﯗ"},{"id":61602,"text":"الْجَحِيمِ","type":"end","c_v1":"ﯘ"},{"id":61603,"text":"(68)","c_v1":"ﯙ"}],"data":{}},{"words":[{"id":61604,"text":"إِنَّهُمْ","c_v1":"ﯚ"},{"id":61605,"text":"أَلْفَوْا","c_v1":"ﯛ"},{"id":61606,"text":"آبَاءَهُمْ","c_v1":"ﯜ"},{"id":61607,"text":"ضَالِّينَ","type":"end","c_v1":"ﯝ"},{"id":61608,"text":"(69)","c_v1":"ﯞ"},{"id":61609,"text":"فَهُمْ","c_v1":"ﯟ"},{"id":61610,"text":"عَلَى","c_v1":"ﯠ"},{"id":61611,"text":"آثَارِهِمْ","c_v1":"ﯡ"},{"id":61612,"text":"يُهْرَعُونَ","type":"end","c_v1":"ﯢ"},{"id":61613,"text":"(70)","c_v1":"ﯣ"}],"data":{}},{"words":[{"id":61614,"text":"وَلَقَدْ","c_v1":"ﯤ"},{"id":61615,"text":"ضَلَّ","c_v1":"ﯥ"},{"id":61616,"text":"قَبْلَهُمْ","c_v1":"ﯦ"},{"id":61617,"text":"أَكْثَرُ","c_v1":"ﯧ"},{"id":61618,"text":"الْأَوَّلِينَ","type":"end","c_v1":"ﯨ"},{"id":61619,"text":"(71)","c_v1":"ﯩ"},{"id":61620,"text":"وَلَقَدْ","c_v1":"ﯪ"},{"id":61621,"text":"أَرْسَلْنَا","c_v1":"ﯫ"},{"id":61622,"text":"فِيهِمْ","c_v1":"ﯬ"}],"data":{}},{"words":[{"id":61623,"text":"مُنْذِرِينَ","type":"end","c_v1":"ﯭ"},{"id":61624,"text":"(72)","c_v1":"ﯮ"},{"id":61625,"text":"فَانْظُرْ","c_v1":"ﯯ"},{"id":61626,"text":"كَيْفَ","c_v1":"ﯰ"},{"id":61627,"text":"كَانَ","c_v1":"ﯱ"},{"id":61628,"text":"عَاقِبَةُ","c_v1":"ﯲ"},{"id":61629,"text":"الْمُنْذَرِينَ","type":"end","c_v1":"ﯳ"},{"id":61630,"text":"(73)","c_v1":"ﯴ"}],"data":{}},{"words":[{"id":61631,"text":"إِلَّا","c_v1":"ﯵ"},{"id":61632,"text":"عِبَادَ","c_v1":"ﯶ"},{"id":61633,"text":"اللَّهِ","c_v1":"ﯷ"},{"id":61634,"text":"الْمُخْلَصِينَ","type":"end","c_v1":"ﯸ"},{"id":61635,"text":"(74)","c_v1":"ﯹ"},{"id":61636,"text":"وَلَقَدْ","c_v1":"ﯺ"},{"id":61637,"text":"نَادَانَا","c_v1":"ﯻ"},{"id":61638,"text":"نُوحٌ","c_v1":"ﯼ"},{"id":61639,"text":"فَلَنِعْمَ","c_v1":"ﯽ"}],"data":{}},{"words":[{"id":61640,"text":"الْمُجِيبُونَ","type":"end","c_v1":"ﯾ"},{"id":61641,"text":"(75)","c_v1":"ﯿ"},{"id":61642,"text":"وَنَجَّيْنَاهُ","c_v1":"ﰀ"},{"id":61643,"text":"وَأَهْلَهُ","c_v1":"ﰁ"},{"id":61644,"text":"مِنَ","c_v1":"ﰂ"},{"id":61645,"text":"الْكَرْبِ","c_v1":"ﰃ"},{"id":61646,"text":"الْعَظِيمِ","type":"end","c_v1":"ﰄ"},{"id":61647,"text":"(76)","c_v1":"ﰅ"}],"data":{}}],"header":"سُورَةُ الصَّافَّاتِ","juz":23,"ayahs":[{"ayah":"يقول اانك لمن المصدقين","suraName":"الصافات","ayahId":52},{"ayah":"ااذا متنا وكنا ترابا وعظاما اانا لمدينون","suraName":"الصافات","ayahId":53},{"ayah":"قال هل انتم مطلعون","suraName":"الصافات","ayahId":54},{"ayah":"فاطلع فراه في سواء الجحيم","suraName":"الصافات","ayahId":55},{"ayah":"قال تالله ان كدت لتردين","suraName":"الصافات","ayahId":56},{"ayah":"ولولا نعمة ربي لكنت من المحضرين","suraName":"الصافات","ayahId":57},{"ayah":"افما نحن بميتين","suraName":"الصافات","ayahId":58},{"ayah":"الا موتتنا الاولى وما نحن بمعذبين","suraName":"الصافات","ayahId":59},{"ayah":"ان هذا لهو الفوز العظيم","suraName":"الصافات","ayahId":60},{"ayah":"لمثل هذا فليعمل العاملون","suraName":"الصافات","ayahId":61},{"ayah":"اذلك خير نزلا ام شجرة الزقوم","suraName":"الصافات","ayahId":62},{"ayah":"انا جعلناها فتنة للظالمين","suraName":"الصافات","ayahId":63},{"ayah":"انها شجرة تخرج في اصل الجحيم","suraName":"الصافات","ayahId":64},{"ayah":"طلعها كانه رءوس الشياطين","suraName":"الصافات","ayahId":65},{"ayah":"فانهم لاكلون منها فمالئون منها البطون","suraName":"الصافات","ayahId":66},{"ayah":"ثم ان لهم عليها لشوبا من حميم","suraName":"الصافات","ayahId":67},{"ayah":"ثم ان مرجعهم لالى الجحيم","suraName":"الصافات","ayahId":68},{"ayah":"انهم الفوا اباءهم ضالين","suraName":"الصافات","ayahId":69},{"ayah":"فهم على اثارهم يهرعون","suraName":"الصافات","ayahId":70},{"ayah":"ولقد ضل قبلهم اكثر الاولين","suraName":"الصافات","ayahId":71},{"ayah":"ولقد ارسلنا فيهم منذرين","suraName":"الصافات","ayahId":72},{"ayah":"فانظر كيف كان عاقبة المنذرين","suraName":"الصافات","ayahId":73},{"ayah":"الا عباد الله المخلصين","suraName":"الصافات","ayahId":74},{"ayah":"ولقد نادانا نوح فلنعم المجيبون","suraName":"الصافات","ayahId":75},{"ayah":"ونجيناه واهله من الكرب العظيم","suraName":"الصافات","ayahId":76}]}