{"page":353,"lines":[{"words":[{"id":48139,"text":"فَإِنْ","c_v1":"ﭑ"},{"id":48140,"text":"لَمْ","c_v1":"ﭒ"},{"id":48141,"text":"تَجِدُوا","c_v1":"ﭓ"},{"id":48142,"text":"فِيهَا","c_v1":"ﭔ"},{"id":48143,"text":"أَحَدًا","c_v1":"ﭕ"},{"id":48144,"text":"فَلَا","c_v1":"ﭖ"},{"id":48145,"text":"تَدْخُلُوهَا","c_v1":"ﭗ"},{"id":48146,"text":"حَتَّى","c_v1":"ﭘ"},{"id":48147,"text":"يُؤْذَنَ","c_v1":"ﭙ"},{"id":48148,"text":"لَكُمْ","c_v1":"ﭚﭛ"},{"id":48149,"text":"وَإِنْ","c_v1":"ﭜ"}],"data":{}},{"words":[{"id":48150,"text":"قِيلَ","c_v1":"ﭝ"},{"id":48151,"text":"لَكُمُ","c_v1":"ﭞ"},{"id":48152,"text":"ارْجِعُوا","c_v1":"ﭟ"},{"id":48153,"text":"فَارْجِعُوا","c_v1":"ﭠﭡ"},{"id":48154,"text":"هُوَ","c_v1":"ﭢ"},{"id":48155,"text":"أَزْكَى","c_v1":"ﭣ"},{"id":48156,"text":"لَكُمْ","c_v1":"ﭤﭥ"},{"id":48157,"text":"وَاللَّهُ","c_v1":"ﭦ"},{"id":48158,"text":"بِمَا","c_v1":"ﭧ"},{"id":48159,"text":"تَعْمَلُونَ","c_v1":"ﭨ"}],"data":{}},{"words":[{"id":48160,"text":"عَلِيمٌ","type":"end","c_v1":"ﭩ"},{"id":48161,"text":"(28)","c_v1":"ﭪ"},{"id":48162,"text":"لَيْسَ","c_v1":"ﭫ"},{"id":48163,"text":"عَلَيْكُمْ","c_v1":"ﭬ"},{"id":48164,"text":"جُنَاحٌ","c_v1":"ﭭ"},{"id":48165,"text":"أَنْ","c_v1":"ﭮ"},{"id":48166,"text":"تَدْخُلُوا","c_v1":"ﭯ"},{"id":48167,"text":"بُيُوتًا","c_v1":"ﭰ"},{"id":48168,"text":"غَيْرَ","c_v1":"ﭱ"},{"id":48169,"text":"مَسْكُونَةٍ","c_v1":"ﭲ"}],"data":{}},{"words":[{"id":48170,"text":"فِيهَا","c_v1":"ﭳ"},{"id":48171,"text":"مَتَاعٌ","c_v1":"ﭴ"},{"id":48172,"text":"لَكُمْ","c_v1":"ﭵﭶ"},{"id":48173,"text":"وَاللَّهُ","c_v1":"ﭷ"},{"id":48174,"text":"يَعْلَمُ","c_v1":"ﭸ"},{"id":48175,"text":"مَا","c_v1":"ﭹ"},{"id":48176,"text":"تُبْدُونَ","c_v1":"ﭺ"},{"id":48177,"text":"وَمَا","c_v1":"ﭻ"},{"id":48178,"text":"تَكْتُمُونَ","type":"end","c_v1":"ﭼ"},{"id":48179,"text":"(29)","c_v1":"ﭽ"}],"data":{}},{"words":[{"id":48180,"text":"قُلْ","c_v1":"ﭾ"},{"id":48181,"text":"لِلْمُؤْمِنِينَ","c_v1":"ﭿ"},{"id":48182,"text":"يَغُضُّوا","c_v1":"ﮀ"},{"id":48183,"text":"مِنْ","c_v1":"ﮁ"},{"id":48184,"text":"أَبْصَارِهِمْ","c_v1":"ﮂ"},{"id":48185,"text":"وَيَحْفَظُوا","c_v1":"ﮃ"},{"id":48186,"text":"فُرُوجَهُمْ","c_v1":"ﮄﮅ"}],"data":{}},{"words":[{"id":48187,"text":"ذَلِكَ","c_v1":"ﮆ"},{"id":48188,"text":"أَزْكَى","c_v1":"ﮇ"},{"id":48189,"text":"لَهُمْ","c_v1":"ﮈﮉ"},{"id":48190,"text":"إِنَّ","c_v1":"ﮊ"},{"id":48191,"text":"اللَّهَ","c_v1":"ﮋ"},{"id":48192,"text":"خَبِيرٌ","c_v1":"ﮌ"},{"id":48193,"text":"بِمَا","c_v1":"ﮍ"},{"id":48194,"text":"يَصْنَعُونَ","type":"end","c_v1":"ﮎ"},{"id":48195,"text":"(30)","c_v1":"ﮏ"},{"id":48196,"text":"وَقُلْ","c_v1":"ﮐ"},{"id":48197,"text":"لِلْمُؤْمِنَاتِ","c_v1":"ﮑ"}],"data":{}},{"words":[{"id":48198,"text":"يَغْضُضْنَ","c_v1":"ﮒ"},{"id":48199,"text":"مِنْ","c_v1":"ﮓ"},{"id":48200,"text":"أَبْصَارِهِنَّ","c_v1":"ﮔ"},{"id":48201,"text":"وَيَحْفَظْنَ","c_v1":"ﮕ"},{"id":48202,"text":"فُرُوجَهُنَّ","c_v1":"ﮖ"},{"id":48203,"text":"وَلَا","c_v1":"ﮗ"},{"id":48204,"text":"يُبْدِينَ","c_v1":"ﮘ"}],"data":{}},{"words":[{"id":48205,"text":"زِينَتَهُنَّ","c_v1":"ﮙ"},{"id":48206,"text":"إِلَّا","c_v1":"ﮚ"},{"id":48207,"text":"مَا","c_v1":"ﮛ"},{"id":48208,"text":"ظَهَرَ","c_v1":"ﮜ"},{"id":48209,"text":"مِنْهَا","c_v1":"ﮝﮞ"},{"id":48210,"text":"وَلْيَضْرِبْنَ","c_v1":"ﮟ"},{"id":48211,"text":"بِخُمُرِهِنَّ","c_v1":"ﮠ"},{"id":48212,"text":"عَلَى","c_v1":"ﮡ"},{"id":48213,"text":"جُيُوبِهِنَّ","c_v1":"ﮢﮣ"}],"data":{}},{"words":[{"id":48214,"text":"وَلَا","c_v1":"ﮤ"},{"id":48215,"text":"يُبْدِينَ","c_v1":"ﮥ"},{"id":48216,"text":"زِينَتَهُنَّ","c_v1":"ﮦ"},{"id":48217,"text":"إِلَّا","c_v1":"ﮧ"},{"id":48218,"text":"لِبُعُولَتِهِنَّ","c_v1":"ﮨ"},{"id":48219,"text":"أَوْ","c_v1":"ﮩ"},{"id":48220,"text":"آبَائِهِنَّ","c_v1":"ﮪ"},{"id":48221,"text":"أَوْ","c_v1":"ﮫ"}],"data":{}},{"words":[{"id":48222,"text":"آبَاءِ","c_v1":"ﮬ"},{"id":48223,"text":"بُعُولَتِهِنَّ","c_v1":"ﮭ"},{"id":48224,"text":"أَوْ","c_v1":"ﮮ"},{"id":48225,"text":"أَبْنَائِهِنَّ","c_v1":"ﮯ"},{"id":48226,"text":"أَوْ","c_v1":"ﮰ"},{"id":48227,"text":"أَبْنَاءِ","c_v1":"ﮱ"},{"id":48228,"text":"بُعُولَتِهِنَّ","c_v1":"ﯓ"}],"data":{}},{"words":[{"id":48229,"text":"أَوْ","c_v1":"ﯔ"},{"id":48230,"text":"إِخْوَانِهِنَّ","c_v1":"ﯕ"},{"id":48231,"text":"أَوْ","c_v1":"ﯖ"},{"id":48232,"text":"بَنِي","c_v1":"ﯗ"},{"id":48233,"text":"إِخْوَانِهِنَّ","c_v1":"ﯘ"},{"id":48234,"text":"أَوْ","c_v1":"ﯙ"},{"id":48235,"text":"بَنِي","c_v1":"ﯚ"},{"id":48236,"text":"أَخَوَاتِهِنَّ","c_v1":"ﯛ"},{"id":48237,"text":"أَوْ","c_v1":"ﯜ"},{"id":48238,"text":"نِسَائِهِنَّ","c_v1":"ﯝ"}],"data":{}},{"words":[{"id":48239,"text":"أَوْ","c_v1":"ﯞ"},{"id":48240,"text":"مَا","c_v1":"ﯟ"},{"id":48241,"text":"مَلَكَتْ","c_v1":"ﯠ"},{"id":48242,"text":"أَيْمَانُهُنَّ","c_v1":"ﯡ"},{"id":48243,"text":"أَوِ","c_v1":"ﯢ"},{"id":48244,"text":"التَّابِعِينَ","c_v1":"ﯣ"},{"id":48245,"text":"غَيْرِ","c_v1":"ﯤ"},{"id":48246,"text":"أُولِي","c_v1":"ﯥ"},{"id":48247,"text":"الْإِرْبَةِ","c_v1":"ﯦ"},{"id":48248,"text":"مِنَ","c_v1":"ﯧ"}],"data":{}},{"words":[{"id":48249,"text":"الرِّجَالِ","c_v1":"ﯨ"},{"id":48250,"text":"أَوِ","c_v1":"ﯩ"},{"id":48251,"text":"الطِّفْلِ","c_v1":"ﯪ"},{"id":48252,"text":"الَّذِينَ","c_v1":"ﯫ"},{"id":48253,"text":"لَمْ","c_v1":"ﯬ"},{"id":48254,"text":"يَظْهَرُوا","c_v1":"ﯭ"},{"id":48255,"text":"عَلَى","c_v1":"ﯮ"},{"id":48256,"text":"عَوْرَاتِ","c_v1":"ﯯ"},{"id":48257,"text":"النِّسَاءِ","c_v1":"ﯰﯱ"}],"data":{}},{"words":[{"id":48258,"text":"وَلَا","c_v1":"ﯲ"},{"id":48259,"text":"يَضْرِبْنَ","c_v1":"ﯳ"},{"id":48260,"text":"بِأَرْجُلِهِنَّ","c_v1":"ﯴ"},{"id":48261,"text":"لِيُعْلَمَ","c_v1":"ﯵ"},{"id":48262,"text":"مَا","c_v1":"ﯶ"},{"id":48263,"text":"يُخْفِينَ","c_v1":"ﯷ"},{"id":48264,"text":"مِنْ","c_v1":"ﯸ"},{"id":48265,"text":"زِينَتِهِنَّ","c_v1":"ﯹﯺ"},{"id":48266,"text":"وَتُوبُوا","c_v1":"ﯻ"}],"data":{}},{"words":[{"id":48267,"text":"إِلَى","c_v1":"ﯼ"},{"id":48268,"text":"اللَّهِ","c_v1":"ﯽ"},{"id":48269,"text":"جَمِيعًا","c_v1":"ﯾ"},{"id":48270,"text":"أَيُّهَ","c_v1":"ﯿ"},{"id":48271,"text":"الْمُؤْمِنُونَ","c_v1":"ﰀ"},{"id":48272,"text":"لَعَلَّكُمْ","c_v1":"ﰁ"},{"id":48273,"text":"تُفْلِحُونَ","type":"end","c_v1":"ﰂ"},{"id":48274,"text":"(31)","c_v1":"ﰃ"}],"data":{}}],"header":"سُورَةُ النُّورِ","juz":18,"ayahs":[{"ayah":"فان لم تجدوا فيها احدا فلا تدخلوها حتى يؤذن لكم وان قيل لكم ارجعوا فارجعوا هو ازكى لكم والله بما تعملون عليم","suraName":"النور","ayahId":28},{"ayah":"ليس عليكم جناح ان تدخلوا بيوتا غير مسكونة فيها متاع لكم والله يعلم ما تبدون وما تكتمون","suraName":"النور","ayahId":29},{"ayah":"قل للمؤمنين يغضوا من ابصارهم ويحفظوا فروجهم ذلك ازكى لهم ان الله خبير بما يصنعون","suraName":"النور","ayahId":30},{"ayah":"وقل للمؤمنات يغضضن من ابصارهن ويحفظن فروجهن ولا يبدين زينتهن الا ما ظهر منها وليضربن بخمرهن على جيوبهن ولا يبدين زينتهن الا لبعولتهن او ابائهن او اباء بعولتهن او ابنائهن او ابناء بعولتهن او اخوانهن او بني اخوانهن او بني اخواتهن او نسائهن او ما ملكت ايمانهن او التابعين غير اولي الاربة من الرجال او الطفل الذين لم يظهروا على عورات النساء ولا يضربن بارجلهن ليعلم ما يخفين من زينتهن وتوبوا الى الله جميعا ايه المؤمنون لعلكم تفلحون","suraName":"النور","ayahId":31}]}